Workbook

Sheet Leidos antes
A1: Titulo | B1: Autor | C1: Origen | D1: Fecha Inicio | E1: Fecha Fin | F1: Paginas | G1: Tipo | H1: Puntuación (del 1 al 10)
A2: Soldados de Salamina | B2: Javier Cercas | G2: Novela | H2: 6

Sheet Leidos 2008
A1: Titulo | B1: Autor | C1: Origen | D1: Fecha Inicio | E1: Fecha Fin | F1: Paginas | G1: Tipo | H1: Puntuación (del 1 al 10)
A2: La flecha del tiempo o La naturaleza de la ofensa | B2: Martin Amis | C2: N AMI fle | D2: 39813 | E2: 39813 | G2: Novela | H2: 8
A3: Jpod | B3: Douglas Coupland | C3: N COU jpo | D3: 39813 | E3: 39813 | G3: Novela | H3: 7
A4: Neuromante | B4: William Gibson | C4: N GIB neu | D4: 39813 | E4: 39813 | G4: Novela | H4: 5

Sheet Leidos 2009
A1: Titulo | B1: Autor | C1: Origen | D1: Fecha Inicio | E1: Fecha Fin | F1: Paginas | G1: Tipo | H1: Puntuación (del 1 al 10)
A2: El mono desnudo | B2: Desmond Morris | C2: 572 MOR mon | D2: 39824 | E2: 39827 | F2: 283 | G2: Ensayo | H2: 6
A3: Fahrenheit 451 | B3: Ray Bradbury | C3: N BRA far | D3: 39827 | E3: 39832 | F3: 183 | G3: Novela | H3: 6
A4: Las siete hijas de Eva | B4: Bryan Sykes | C4: 572 SYK sie | D4: 39832 | E4: 39841 | F4: 302 | G4: Ensayo | H4: 5
A5: Gomorra: un viaje al imperio económico y al sueño de poder de la Camorra | B5: Roberto Saviano | C5: Propio | D5: 39841 | E5: 39846 | F5: 324 | G5: Ensayo | H5: 8
A6: El viaje del elefante | B6: José Saramago | C6: Propio | D6: 39846 | E6: 39848 | F6: 270 | G6: Novela | H6: 9
A7: El porqué de las cosas | B7: Quim Monzó | C7: N MON por | D7: 39848 | E7: 39854 | F7: 138 | G7: Novela | H7: 6
A8: El sexto invierno | B8: Douglas Orgill y John Gribbin | C8: N ORG sex | D8: 39854 | E8: 39867 | F8: 412 | G8: Novela | H8: 5
A9: Kafka on the Shore | B9: Haruki Murakami | C9: N MUR kaf | D9: 39867 | E9: 39881 | F9: 584 | G9: Novela | H9: 6.5
A10: 2666 | B10: Roberto Bolaño | C10: Propio | D10: 39881 | E10: 39889 | F10: 1125 | G10: Novela | H10: 9.5
A11: Genoma: la autobiografía de una especie en 23 capítulos | B11: Matt Ridley | C11: 575 RID gen | D11: 39889 | E11: 39895 | F11: 388 | G11: Ensayo | H11: 6.5
A12: Trece campanadas | B12: Suso de Toro | C12: N TOR tre | D12: 39895 | E12: 39902 | F12: 397 | G12: Novela | H12: 4.5
A13: Piratas, corsarios, bucaneros y filibusteros | B13: Manuel Lucena Salmoral | C13: 910 LUC pir | D13: 39902 | E13: 39909 | F13: 313 | G13: Historia | H13: 5
A14: El antropólogo inocente: notas desde una choza de barro | B14: Nigel Barley | C14: 39 BAR ant | D14: 39909 | E14: 39918 | F14: 234 | G14: Ensayo | H14: 7
A15: La isla de los ciegos al color | B15: Oliver Sacks | C15: 617 SAC isl | D15: 39918 | E15: 39923 | F15: 312 | G15: Ensayo | H15: 6.5
A16: Indios carapálidas | B16: Ricardo Herren | C16: 97/98 HER ind | D16: 39923 | E16: 39930 | F16: 184 | G16: Ensayo | H16: 7
A17: Un trabajo muy sucio | B17: Christopher Moore | C17: Prestado | D17: 39930 | E17: 39935 | F17: 348 | G17: Novela | H17: 7.5
A18: En picado | B18: Nick Hornby | C18: N HOR enp | D18: 39935 | E18: 39939 | F18: 321 | G18: Novela | H18: 8
A19: La vida en las ventanas | B19: Andrés Neuman | C19: N NEU vid | D19: 39939 | E19: 39944 | F19: 199 | G19: Novela | H19: 6.5
A20: La piel fría | B20: Albert Sánchez Piñol | C20: N SAN pie | D20: 39944 | E20: 39956 | F20: 283 | G20: Novela | H20: 7.5
A21: El médico | B21: Noah Gordon | C21: Propio | D21: 39956 | E21: 39969 | F21: 873 | G21: Novela | H21: 6
A22: La isla de cemento | B22: J. G. Ballard | C22: N BAL isl | D22: 39969 | E22: 39974 | F22: 174 | G22: Novela | H22: 4
A23: Historias de Londres | B23: Enric González | C23: N GON his | D23: 39974 | E23: 39984 | F23: 185 | G23: Novela | H23: 6
A24: La chica que soñaba con una cerilla y un bidón de gasolina | B24: Stieg Larsson | C24: Prestado | D24: 39984 | E24: 39989 | F24: 752 | G24: Novela | H24: 8
A25: Polvo eres: peripecias y extravagancias de algunos cadáveres inquietos | B25: Nieves Concostrina | C25: B CON pol | D25: 39989 | E25: 39994 | F25: 394 | G25: Historia | H25: 6
A26: Jennifer Gobierno | B26: Max Barry | C26: N BAR jen | D26: 39994 | E26: 40001 | F26: 323 | G26: Novela | H26: 5
A27: Patas arriba | B27: Eduardo Galeano | C27: N GAL pat | D27: 40001 | E27: 40008 | F27: 365 | G27: Novela | H27: 7
A28: El corazón de las tinieblas | B28: Joseph Conrad | C28: Prestado | D28: 40008 | E28: 40013 | F28: 139 | G28: Novela | H28: 5
A29: La maravillosa vida breve de Óscar Wao | B29: Junot Díaz | C29: Prestado | D29: 40013 | E29: 40021 | F29: 309 | G29: Novela | H29: 8
A30: Testigo de raza: un negro en la Alemania nazi | B30: Hans j. Massaquoi | C30: Propio | D30: 40021 | E30: 40022 | F30: 540 | G30: Biografía | H30: 3
A31: El Rey Rata | B31: China Miéville | C31: N MIE rey | D31: 40022 | E31: - | F31: 311 | G31: Novela | H31: -
A32: La batalla de Creta | B32: Antony Beevor | C32: 94 BEE bat | D32: 40029 | E32: 40035 | F32: 414 | G32: Historia | H32: 7
A33: El conde-duque de Olivares | B33: J.H. Elliott | C33: Propio | D33: 40035 | E33: 40061 | F33: 924 | G33: Historia | H33: 8.5
A34: Londres: una biografía | B34: Peter Ackroyd | C34: 941 ACK lon | D34: 40052 | E34: - | F34: 1007 | G34: Ensayo | H34: 6
A35: Patria | B35: Robert Harris | C35: N HAR pat | D35: 40062 | E35: 40065 | F35: 406 | G35: Novela | H35: 6
A36: La aventura de las lenguas en Occidente | B36: Henriette Walter | C36: 81(09) WAL ave | D36: 40066 | E36: 40077 | F36: 531 | G36: Ensayo | H36: 4.5
A37: La tercera ola | B37: Alvin Toffler | C37: 008 TOF ter | D37: 40079 | E37: - | F37: 494 | G37: Ensayo | H37: 3 | I37: Interesante pero obsoleto
A38: Los santos inocentes | B38: Miguel Delibes | C38: N DEL san | D38: 40085 | E38: 40085 | F38: 175 | G38: Novela | H38: 8
A39: American Psycho | B39: Bret Easton Ellis | C39: N ELL ame | D39: 40086 | E39: 40102 | F39: 477 | G39: Novela | H39: 7.5
A40: La reina en el palacio de las corrientes de aire | B40: Stieg Larsson | C40: Propio | D40: 40102 | E40: 40108 | F40: 812 | G40: Novela | H40: 8.5
A41: Los detectives salvajes | B41: Roberto Bolaño | C41: N BOL det | D41: 40108 | E41: 40122 | F41: 609 | G41: Novela | H41: 9
A42: Crónica de una muerte anunciada | B42: Gabriel García Márquez | C42: Prestado | D42: 40113 | E42: 40126 | F42: 135 | G42: Novela | H42: 7.5
A43: Los guerreros del oro: el tesoro de Yamashita y la financiación de la guerra fría | B43: Sterling y Peggy Seagrave | C43: 343 SEA gue | D43: 40123 | E43: 40134 | F43: 488 | G43: Historia | H43: 6
A44: El hombre en el castillo | B44: Philip K. Dick | C44: N DIC hom | D44: 40130 | E44: 40135 | F44: 262 | G44: Novela | H44: 6
A45: La caida del museo británico | B45: David Lodge | C45: N LOD cai | D45: 40136 | E45: 40140 | F45: 187 | G45: Novela | H45: 7
A46: Matadero cinco o La cruzada de los niños | B46: Kurt Vonnegut | C46: N VON mat | D46: 40141 | E46: 40145 | F46: 188 | G46: Novela | H46: 8.5
A47: Microcosmos : cuatro mil millones de años de evolución desde nuestros ancestros microbianos | B47: Lynn Margulis | C47: 575 MAR mic | D47: 40145 | E47: 40150 | F47: 317 | G47: Ensayo | H47: 8
A48: Cómo ser buenos | B48: Nick Hornby | C48: N HOR com | D48: 40151 | E48: 40162 | F48: 330 | G48: Novela | H48: 7
A49: Amuleto | B49: Roberto Bolaño | C49: N BOL amu | D49: 40164 | E49: 40168 | F49: 154 | G49: Novela | H49: 7
... A51: La España imperial, 1469-1716 | B51: J.H. Elliott | C51: 946 ELL esp | D51: 40175 | E51: 40185 | F51: 454 | G51: Historia | H51: 8
E53: =COUNT(E2:E51) -> 47 | F53: =SUM(F2:F51) -> 19728 | H53: =AVERAGE(H2:H51) -> 6.6097561

Sheet Leidos 2010
A1: Titulo | B1: Autor | C1: Origen | D1: Fecha Inicio | E1: Fecha Fin | F1: Paginas | G1: Tipo | H1: Puntuación (del 1 al 10) | J1: Paginas efectivas leídas | K1: Libro Leido? | L1: Autor leido?
A2: El Proceso | B2: Franz Kafka | C2: Prestado | D2: 40135 | E2: 40442 | F2: 280 | G2: Novela | H2: 7 | J2: =IF(ISBLANK(E2),0,F2) -> 280 | K2: =IF(ISBLANK(E2),0,1) -> 1 | L2: =IF(ISBLANK(E2)," ",B2) -> Franz Kafka
A3: Simon´s cat | B3: Simon Tofield | C3: Propio | D3: 40184 | E3: 40184 | F3: 240 | G3: Comic | H3: 8 | J3: =IF(ISBLANK(E3),0,F3) -> 240 | K3: =IF(ISBLANK(E3),0,1) -> 1 | L3: =IF(ISBLANK(E3)," ",B3) -> Simon Tofield
A4: Diario : una novela | B4: Chuck Palahniuk | C4: N PAL dia | D4: 40186 | E4: 40192 | F4: 275 | G4: Novela | H4: 7.5 | J4: =IF(ISBLANK(E4),0,F4) -> 275 | K4: =IF(ISBLANK(E4),0,1) -> 1 | L4: =IF(ISBLANK(E4)," ",B4) -> Chuck Palahniuk
A5: Hitler, la novela gráfica | B5: Shigeru Mizuki | C5: Propio | D5: 40188 | E5: 40206 | F5: 208 | G5: Comic | H5: 9 | J5: =IF(ISBLANK(E5),0,F5) -> 208 | K5: =IF(ISBLANK(E5),0,1) -> 1 | L5: =IF(ISBLANK(E5)," ",B5) -> Shigeru Mizuki
A6: El año de la muerte de Ricardo Reis | B6: José Saramago | C6: N SAR año | D6: 40193 | E6: 40204 | F6: 527 | G6: Novela | H6: 7 | J6: =IF(ISBLANK(E6),0,F6) -> 527 | K6: =IF(ISBLANK(E6),0,1) -> 1 | L6: =IF(ISBLANK(E6)," ",B6) -> José Saramago
A7: Pregúntale al polvo | B7: John Fante | C7: N FAN pre | D7: 40205 | E7: 40210 | F7: 205 | G7: Novela | H7: 6 | J7: =IF(ISBLANK(E7),0,F7) -> 205 | K7: =IF(ISBLANK(E7),0,1) -> 1 | L7: =IF(ISBLANK(E7)," ",B7) -> John Fante
A8: Crimen y castigo | B8: Fedor Dostoyevski | C8: N DOS cri | D8: 40211 | E8: 40225 | F8: 703 | G8: Novela | H8: 8.5 | J8: =IF(ISBLANK(E8),0,F8) -> 703 | K8: =IF(ISBLANK(E8),0,1) -> 1 | L8: =IF(ISBLANK(E8)," ",B8) -> Fedor Dostoyevski
A9: Guía del Autoestopista Galáctico | B9: Douglas Adams | C9: ebook | D9: 40222 | E9: 40227 | F9: 174 | G9: Novela | H9: 8 | J9: =IF(ISBLANK(E9),0,F9) -> 174 | K9: =IF(ISBLANK(E9),0,1) -> 1 | L9: =IF(ISBLANK(E9)," ",B9) -> Douglas Adams
A10: La carretera | B10: Cormac McCarthy | C10: ebook | D10: 40228 | E10: 40233 | F10: 210 | G10: Novela | H10: 8 | J10: =IF(ISBLANK(E10),0,F10) -> 210 | K10: =IF(ISBLANK(E10),0,1) -> 1 | L10: =IF(ISBLANK(E10)," ",B10) -> Cormac McCarthy
A11: Q | B11: Luther Blissett | C11: ebook | D11: 40233 | E11: 40248 | F11: 641 | G11: Novela | H11: 7.5 | J11: =IF(ISBLANK(E11),0,F11) -> 641 | K11: =IF(ISBLANK(E11),0,1) -> 1 | L11: =IF(ISBLANK(E11)," ",B11) -> Luther Blissett
A12: La aventura de los godos | B12: Juan Antonio Cebrián | C12: ebook | D12: 40236 | E12: 40249 | F12: 232 | G12: Ensayo | H12: 7 | J12: =IF(ISBLANK(E12),0,F12) -> 232 | K12: =IF(ISBLANK(E12),0,1) -> 1 | L12: =IF(ISBLANK(E12)," ",B12) -> Juan Antonio Cebrián
A13: La mula | B13: Juan Eslava Galán | C13: ebook | D13: 40249 | E13: 40252 | F13: 272 | G13: Novela | H13: 7 | J13: =IF(ISBLANK(E13),0,F13) -> 272 | K13: =IF(ISBLANK(E13),0,1) -> 1 | L13: =IF(ISBLANK(E13)," ",B13) -> Juan Eslava Galán
... A57: En el camino | B57: Jack Kerouac | C57: ebook | D57: 40515 | E57: 40533 | F57: 368 | G57: Novela | H57: 8 | J57: =IF(ISBLANK(E57),0,F57) -> 368 | K57: =IF(ISBLANK(E57),0,1) -> 1 | L57: =IF(ISBLANK(E57)," ",B57) -> Jack Kerouac
F58: =SUM(F2:F57) -> 20051 | H58: =AVERAGE(H2:H57) -> 7.0625
A59: Estadísticas
A60: Nº Páginas Leídas | B60: Libros Leídos | C60: Media páginas por libro | D60: Autor más leido | E60: Tipo más leido
A61: =SUM(J2:J57) -> 20051 | B61: =SUM(K2:K57) -> 56 | C61: =ROUND(A61/B61,0) -> 358 | D61: {=INDEX(L2:L57,MAX(IF(COUNTIF($L$2:$L$57,L2:L57)=LARGE(COUNTIF($L$2:$L$57,L2:L57),1),ROW(L2:L57)*0))*0.1)} -> Franz Kafka

Sheet Leidos 2011
A1: Titulo | B1: Autor | C1: Origen | D1: Fecha Inicio | E1: Fecha Fin | F1: Paginas | G1: Tipo | H1: Puntuación (del 1 al 10) | I1: Num leidos | J1: Autor
A2: Política de hechos consumados | B2: Nacho Vegas | C2: Propio | D2: 40151 | E2: 40616 | F2: 94 | G2: Relatos | H2: 6 | I2: =NA() -> #N/A | J2: =B2 -> Nacho Vegas
A3: Revista Orsai | B3: Varios | C3: Revista | D3: 40553 | E3: 40612 | F3: 180 | G3: Revista | H3: 8 | I3: =NA() -> #N/A | J3: =B3 -> Varios
A4: El Misterio De Los Hititas | B4: C. W Ceram | C4: ebook | D4: 40513 | E4: 40550 | F4: 283 | G4: Historia | H4: 6 | I4: =NA() -> #N/A | J4: =B4 -> C. W Ceram
A5: Ciclo Barroco: Azogue | B5: Neal Stephenson | C5: ebook | D5: 40550 | E5: 40563 | F5: 400 | G5: Novela | H5: 8 | I5: =NA() -> #N/A | J5: =B5 -> Neal Stephenson
A6: Los Simpson y la filosofía | B6: Varios | C6: Propio | D6: 40562 | E6: 40590 | F6: 415 | G6: Ensayo | H6: 7.5 | I6: =NA() -> #N/A | J6: =B6 -> Varios
A7: Ciclo Barroco: El rey de los vagabundos | B7: Neal Stephenson | C7: ebook | D7: 40563 | E7: 40573 | F7: 320 | G7: Novela | H7: 8 | I7: =NA() -> #N/A | J7: =B7 -> Neal Stephenson
A8: La historia del mundo en seis tragos | B8: Tom Standage | C8: ebook | D8: 40573 | E8: 40578 | F8: 288 | G8: Ensayo | H8: 7 | I8: =NA() -> #N/A | J8: =B8 -> Tom Standage
A9: Guía Total Berlín | B9: Varios | C9: Propio | D9: 40577 | E9: 40633 | F9: 300 | G9: Guía | H9: 5 | I9: =NA() -> #N/A | J9: =B9 -> Varios
A10: La peste negra | B10: Luis Miguel Guerra | C10: Propio | D10: 40594 | E10: 40596 | F10: 318 | G10: Novela | H10: 6 | I10: =NA() -> #N/A | J10: =B10 -> Luis Miguel Guerra
A11: Ciclo Barroco: Odalisca | B11: Neal Stephenson | C11: ebook | D11: 40597 | E11: 40610 | F11: 360 | G11: Novela | H11: 7.5 | I11: =NA() -> #N/A | J11: =B11 -> Neal Stephenson
A12: Un general confederado de Big Sur | B12: Richard Brautigan | C12: Propio | D12: 40611 | E12: 40616 | F12: 167 | G12: Novela | H12: 6 | I12: =NA() -> #N/A | J12: =B12 -> Richard Brautigan
A13: Diarios de Bicicleta | B13: David Byrne | C13: Propio | D13: 40617 | E13: 40637 | F13: 362 | G13: Diario | H13: 7.5 | I13: =NA() -> #N/A | J13: =B13 -> David Byrne
... A49: Historia del tiempo | B49: Stephen Hawking | C49: ebook | D49: 40903 | E49: 40907 | F49: 248 | G49: Ensayo | H49: 6.5 | I49: =NA() -> #N/A | J49: =B49 -> Stephen Hawking
F50: =SUM(F2:F49) -> 18918 | H50: =AVERAGE(H2:H49) -> 6.98125
A51: Estadísticas
A52: Libros Leídos | B52: Media páginas por libro | C52: Autor más leido | D52: Tipo más leido
A53: =COUNTIF(E2:E49,">0") -> 48 | B53: =ROUND(F50/A53,0) -> 394 | C53: =INDEX(J2:J49,MATCH(MAX(I2:I49),I2:I49,0),1) -> #N/A

Sheet Leidos 2012
A1: Titulo | B1: Autor | C1: Origen | D1: Fecha Inicio | E1: Fecha Fin | F1: Paginas | G1: Tipo | H1: Puntuación (del 1 al 10) | I1: Num leidos | J1: Autor
A2: Revista Orsai IV | B2: Varios | C2: Revista | D2: 40750 | E2: 41002 | F2: 206 | G2: Revista | H2: 5 | I2: =NA() -> #N/A | J2: =B2 -> Varios
A3: 54 | B3: Wu-ming | C3: ebook | D3: 40910 | E3: 40924 | F3: 600 | G3: Novela | H3: 7 | I3: =NA() -> #N/A | J3: =B3 -> Wu-ming
A4: Porno | B4: Irvine Welsh | C4: ebook | D4: 40925 | E4: 40940 | F4: 320 | G4: Novela | H4: 8 | I4: =NA() -> #N/A | J4: =B4 -> Irvine Welsh
A5: En casa | B5: Bill Bryson | C5: Propio | D5: 40930 | E5: 40947 | F5: 672 | G5: Divulgación | H5: 8 | I5: =NA() -> #N/A | J5: =B5 -> Bill Bryson
A6: La Habana para un infante difunto | B6: Guillermo Cabrera Infante | C6: Propio | D6: 40941 | E6: 40965 | F6: 512 | G6: Novela | H6: 7 | I6: =NA() -> #N/A | J6: =B6 -> Guillermo Cabrera Infante
A7: Mata a tus idolos | B7: Luc Sante | C7: Propio | D7: 40951 | E7: 41063 | F7: 397 | G7: Relatos | H7: 6 | I7: =NA() -> #N/A | J7: =B7 -> Luc Sante
A8: Cerdeña | B8: Varios | C8: Propio | D8: 40959 | E8: 41060 | F8: 295 | G8: Guía | H8: 5 | J8: =B8 -> Varios
A9: Superviviente | B9: Chuck Palaniuk | C9: ebook | D9: 40966 | E9: 40969 | F9: 272 | G9: Novela | H9: 8 | I9: =NA() -> #N/A | J9: =B9 -> Chuck Palaniuk
A10: Revista Panenka #5 | B10: Varios | C10: Propio | D10: 40966 | E10: 40978 | F10: 114 | G10: Revista | H10: 7.5 | I10: =NA() -> #N/A | J10: =B10 -> Varios
A11: Los niños del Brasil | B11: Ira Levin | C11: ebook | D11: 40970 | E11: 40975 | F11: 304 | G11: Novela | H11: 6.5 | I11: =NA() -> #N/A | J11: =B11 -> Ira Levin
A12: La estrategia del perro loco | B12: Iñigo Sáenz de Ugarte | C12: ebook | D12: 40975 | E12: 40975 | F12: 50 | G12: Ensayo | H12: 8 | I12: =NA() -> #N/A | J12: =B12 -> Iñigo Sáenz de Ugarte
A13: Anatema | B13: Neal Stephenson | C13: ebook | D13: 40976 | E13: 40991 | F13: 736 | G13: Novela | H13: 8 | I13: =NA() -> #N/A | J13: =B13 -> Neal Stephenson
A14: Fargo Rock City | B14: Chuck Klosterman | C14: Propio | D14: 40986 | E14: 41015 | F14: 352 | G14: Ensayo | H14: 7 | I14: =NA() -> #N/A | J14: =B14 -> Chuck Klosterman
A15: Los Creadores | B15: Daniel J. Boorstin | C15: ebook | D15: 40993 | E15: 41025 | F15: 744 | G15: Ensayo | H15: 8 | I15: =NA() -> #N/A | J15: =B15 -> Daniel J. Boorstin
A16: Dinero | B16: Aristófanes | C16: ebook | D16: 41000 | E16: 41000 | F16: 77 | G16: Teatro | H16: 6 | I16: =NA() -> #N/A | J16: =B16 -> Aristófanes
A17: Todos los hombres del Führer | B17: Ferran Gallego | C17: Propio | D17: 41016 | E17: 41167 | F17: 576 | G17: Historia | H17: 7 | I17: =NA() -> #N/A | J17: =B17 -> Ferran Gallego
A18: La odisea | B18: Homero | C18: ebook | D18: 41025 | E18: 41042 | F18: 501 | G18: Epopeya | H18: 7 | I18: =NA() -> #N/A | J18: =B18 -> Homero
A19: Tierra de sal y arroz | B19: Kim Stanley Robinson | C19: ebook | D19: 41043 | E19: 41052 | F19: 718 | G19: Novela | H19: 5 | I19: =NA() -> #N/A | J19: =B19 -> Kim Stanley Robinson
A20: Del concilio al black power | B20: JdJ | C20: ebook | D20: 41052 | E20: 41052 | F20: 100 | G20: Historia | H20: 8 | I20: =NA() -> #N/A | J20: =B20 -> JdJ
... A41: American Gods | B41: Neil Gaiman | C41: ebook | D41: 41156 | E41: 41163 | F41: 477 | G41: Novela | H41: 8 | I41: =NA() -> #N/A | J41: =B41 -> Neil Gaiman
A42: La primera y la última humanidad | B42: Olaf Stapledon | C42: ebook | D42: 41163 | F42: 304 | G42: Novela | I42: =NA() -> #N/A | J42: =B42 -> Olaf Stapledon
A43: Un gran chico | B43: Nick Hornby | C43: ebook | D43: 41167 | E43: 41175 | F43: 360 | G43: Novela | H43: 7.5 | I43: =NA() -> #N/A | J43: =B43 -> Nick Hornby
A44: Amuleto | B44: Roberto Bolaño | C44: Propio | D44: 41168 | E44: 41216 | F44: 160 | G44: Novela | H44: 7.5 | I44: =NA() -> #N/A | J44: =B44 -> Roberto Bolaño
A45: La caída de Hyperion | B45: Dan Simmons | C45: ebook | D45: 41176 | E45: 41186 | F45: 736 | G45: Novela | H45: 7 | I45: =NA() -> #N/A | J45: =B45 -> Dan Simmons
A46: Col recalentada | B46: Irvine Welsh | C46: ebook | D46: 41187 | E46: 41199 | F46: 288 | G46: Relatos | H46: 7.5 | I46: =NA() -> #N/A | J46: =B46 -> Irvine Welsh
A47: El jardín colgante | B47: Javier Calvo | C47: ebook | D47: 41200 | E47: 41203 | F47: 368 | G47: Novela | H47: 8 | I47: =NA() -> #N/A | J47: =B47 -> Javier Calvo
A48: Verdes Valles, Colinas Rojas: La tierra convulsa | B48: Ramiro Pinilla | C48: ebook | D48: 41203 | E48: 41220 | F48: 744 | G48: Novela | H48: 8 | I48: =NA() -> #N/A | J48: =B48 -> Ramiro Pinilla
A49: Revista Libero #2 | B49: Varios | C49: Propio | D49: 41221 | E49: 41225 | F49: 130 | G49: Revista | H49: 6 | I49: =NA() -> #N/A | J49: =B49 -> Varios
A50: Sobre Camarón | B50: Carlos Lencero | C50: ebook | D50: 41220 | E50: 41227 | F50: 256 | G50: Musica | H50: 6.5 | I50: =NA() -> #N/A | J50: =B50 -> Carlos Lencero
A51: Monstruos invisibles | B51: Chuck Palahniuk | C51: ebook | D51: 41231 | E51: 41239 | F51: 272 | G51: Novela | H51: 5 | I51: =NA() -> #N/A | J51: =B51 -> Chuck Palahniuk
A52: Planeta Gigante | B52: Jack Vance | C52: ebook | D52: 41240 | E52: 41247 | F52: 250 | G52: Novela | H52: 6 | I52: =NA() -> #N/A | J52: =B52 -> Jack Vance
A53: Corona de flores | B53: Javier Calvo | C53: ebook | D53: 41248 | E53: 41258 | F53: 320 | G53: Novela | H53: 7.6 | I53: =NA() -> #N/A | J53: =B53 -> Javier Calvo
A54: Little brother | B54: Cory Doctorow | C54: ebook | D54: 41258 | E54: 41264 | F54: 384 | G54: Novela | H54: 7 | I54: =NA() -> #N/A | J54: =B54 -> Cory Doctorow
F55: =SUM(F2:F54) -> 19868 | H55: =AVERAGE(H2:H54) -> 6.9
A56: Estadísticas
A57: Libros Leídos | B57: Media páginas por libro | C57: Autor más leido | D57: Tipo más leido
A58: =COUNTIF(E2:E54,">0") -> 52 | B58: =ROUND(F55/A58,0) -> 382 | C58: =INDEX(J2:J54,MATCH(MAX(I2:I54),I2:I54,0),1) -> #N/A

Sheet Leídos 2013
A1: Titulo | B1: Autor | C1: Origen | D1: Fecha Inicio | E1: Fecha Fin | F1: Paginas | G1: Tipo | H1: Puntuación (del 1 al 10) | I1: Num leidos | J1: Autor
A2: Pedro Páramo;El llano en llamas | B2: Juan Rulfo | C2: Prestado | D2: 40150 | F2: 222 | G2: Novela | H2: - | I2: =NA() -> #N/A | J2: =B2 -> Juan Rulfo
A3: Ulises | B3: James Joyce | C3: Propio | D3: 40261 | F3: 910 | G3: Novela | H3: - | I3: =NA() -> #N/A | J3: =B3 -> James Joyce
A4: Diccionario del Diablo | B4: Ambrose Bierce | C4: ebook | D4: 40282 | F4: 480 | G4: Novela | H4: - | I4: =NA() -> #N/A | J4: =B4 -> Ambrose Bierce
A5: Johnny got his gun | B5: Dalton Trumbo | C5: ebook | D5: 40296 | F5: 209 | G5: Novela | H5: - | I5: =NA() -> #N/A | J5: =B5 -> Dalton Trumbo
A6: Nuestras hermanas las ratas | B6: Michel Dansel | C6: ebook | D6: 40366 | F6: 160 | G6: Ensayo | H6: - | I6: =NA() -> #N/A | J6: =B6 -> Michel Dansel
A7: Bolaño salvaje | B7: Varios | C7: Propio | D7: 40373 | F7: 502 | G7: Ensayo | H7: - | I7: =NA() -> #N/A | J7: =B7 -> Varios
A8: Historia de la Inquisición | B8: Primitivo Martínez | C8: ebook | D8: 40385 | F8: 384 | G8: Historia | H8: - | I8: =NA() -> #N/A | J8: =B8 -> Primitivo Martínez
A9: Nuestros orígenes | B9: Richard Leakey | C9: ebook | D9: 40438 | F9: 300 | G9: Antropología | H9: - | I9: =NA() -> #N/A | J9: =B9 -> Richard Leakey
A10: El libro de las ilusiones | B10: Paul Auster | C10: Propio | F10: 338 | G10: Novela | H10: - | I10: =NA() -> #N/A | J10: =B10 -> Paul Auster
A11: La búsqueda de la lengua perfecta | B11: Umberto Eco | C11: ebook | D11: 40655 | F11: 300 | G11: Ensayo | H11: - | I11: =NA() -> #N/A | J11: =B11 -> Umberto Eco
A12: La insurrección que viene | B12: Comité invisible | C12: Propio | D12: 40736 | F12: 144 | G12: Ensayo | H12: - | I12: =NA() -> #N/A | J12: =B12 -> Comité invisible
A13: Revista JotDown #1 | B13: Varios | C13: Propio | D13: 41084 | E13: 41365 | F13: 319 | G13: Revista | H13: 8 | I13: =NA() -> #N/A | J13: =B13 -> Varios
A14: El Alamein | B14: Jon Latimer | C14: Propio | D14: 41217 | E14: 41319 | F14: 557 | G14: Historia | H14: 7 | I14: =NA() -> #N/A | J14: =B14 -> Jon Latimer
A15: Los buenos soldados | B15: David Finkel | C15: ebook | D15: 41265 | E15: 41282 | F15: 304 | G15: Historia | H15: 8 | I15: =NA() -> #N/A | J15: =B15 -> David Finkel
A16: Reamde | B16: Neal Stephenson | C16: ebook | D16: 41282 | E16: 41307 | F16: 992 | G16: Novela | H16: 8 | I16: =NA() -> #N/A | J16: =B16 -> Neal Stephenson
A17: El tercer reich | B17: Roberto Bolaño | C17: Propio | D17: 41320 | E17: 41333 | F17: 368 | G17: Novela | H17: 7 | I17: =NA() -> #N/A | J17: =B17 -> Roberto Bolaño
A18: Exitus | B18: Antonio Luque | C18: Propio | D18: 41334 | E18: 41360 | F18: 512 | G18: Novela | H18: 6.5 | I18: =NA() -> #N/A | J18: =B18 -> Antonio Luque
A19: El sueño de una noche de verano | B19: William Shakespeare | C19: ebook | D19: 41361 | E19: 41366 | F19: 144 | G19: Teatro | H19: 7 | I19: =NA() -> #N/A | J19: =B19 -> William Shakespeare
A20: El ávaro | B20: Moliere | C20: ebook | D20: 41366 | E20: 41368 | F20: 128 | G20: Teatro | H20: 7 | I20: =NA() -> #N/A | J20: =B20 -> Moliere
A21: Anabasis | B21: Jenofonte | C21: ebook | D21: 41368 | E21: 41379 | F21: 288 | G21: Historia | H21: 5 | I21: =NA() -> #N/A | J21: =B21 -> Jenofonte
A22: Atenas clásica | B22: Peter Funke | C22: ebook | D22: 41380 | E22: 41381 | F22: 142 | G22: Historia | H22: 8 | I22: =NA() -> #N/A | J22: =B22 -> Peter Funke
A23: La orestiada | B23: Esquilo | C23: ebook | D23: 41382 | E23: 41387 | F23: 200 | G23: Teatro | H23: 6 | I23: =NA() -> #N/A | J23: =B23 -> Esquilo
A24: Guerra Mundial Z | B24: Max Brooks | C24: ebook | D24: 41387 | E24: 41390 | F24: 480 | G24: Novela | H24: 8.6 | I24: =NA() -> #N/A | J24: =B24 -> Max Brooks
... A39: Honrarás a tu padre | B39: Gay Talese | C39: ebook | D39: 41519 | E39: 41620 | F39: 640 | G39: Ensayo | H39: 7 | I39: =NA() -> #N/A | J39: =B39 -> Gay Talese
F41: =SUM(F2:F39) -> 17259
A42: Estadísticas
A43: Libros Leídos | B43: Media páginas por libro | C43: Autor más leido | D43: Tipo más leido
A44: =COUNTIF(E2:E39,">0") -> 27 | B44: =ROUND(F41/A44,0) -> 639 | C44: =INDEX(J2:J39,MATCH(MAX(I2:I39),I2:I39,0),1) -> #N/A

Sheet Leídos 2014
A1: Titulo | B1: Autor | C1: Origen | D1: Fecha Inicio | E1: Fecha Fin | F1: Paginas | G1: Tipo | H1: Puntuación (del 1 al 10) | I1: Num leidos | J1: Autor | K1: Año
A2: Pedro Páramo;El llano en llamas | B2: Juan Rulfo | C2: Prestado | D2: 40150 | F2: 222 | G2: Novela | H2: - | I2: =NA() -> #N/A | J2: =B2 -> Juan Rulfo
A3: Ulises | B3: James Joyce | C3: Propio | D3: 40261 | F3: 910 | G3: Novela | H3: - | I3: =NA() -> #N/A | J3: =B3 -> James Joyce
A4: Diccionario del Diablo | B4: Ambrose Bierce | C4: ebook | D4: 40282 | F4: 480 | G4: Novela | H4: - | I4: =NA() -> #N/A | J4: =B4 -> Ambrose Bierce
A5: Johnny got his gun | B5: Dalton Trumbo | C5: ebook | D5: 40296 | F5: 209 | G5: Novela | H5: - | I5: =NA() -> #N/A | J5: =B5 -> Dalton Trumbo
A6: Nuestras hermanas las ratas | B6: Michel Dansel | C6: ebook | D6: 40366 | F6: 160 | G6: Ensayo | H6: - | I6: =NA() -> #N/A | J6: =B6 -> Michel Dansel
A7: Bolaño salvaje | B7: Varios | C7: Propio | D7: 40373 | F7: 502 | G7: Ensayo | H7: - | I7: =NA() -> #N/A | J7: =B7 -> Varios
A8: Historia de la Inquisición | B8: Primitivo Martínez | C8: ebook | D8: 40385 | F8: 384 | G8: Historia | H8: - | I8: =NA() -> #N/A | J8: =B8 -> Primitivo Martínez
A9: Nuestros orígenes | B9: Richard Leakey | C9: ebook | D9: 40438 | F9: 300 | G9: Antropología | H9: - | I9: =NA() -> #N/A | J9: =B9 -> Richard Leakey
A10: El libro de las ilusiones | B10: Paul Auster | C10: Propio | F10: 338 | G10: Novela | H10: - | I10: =NA() -> #N/A | J10: =B10 -> Paul Auster
A11: La búsqueda de la lengua perfecta | B11: Umberto Eco | C11: ebook | D11: 40655 | F11: 300 | G11: Ensayo | H11: - | I11: =NA() -> #N/A | J11: =B11 -> Umberto Eco
A12: La insurrección que viene | B12: Comité invisible | C12: Propio | D12: 40736 | F12: 144 | G12: Ensayo | H12: - | I12: =NA() -> #N/A | J12: =B12 -> Comité invisible
A13: Mongoliad | B13: Neal Stephenson | C13: Propio | D13: 41537 | E13: 41666 | F13: 473 | G13: Novela | H13: 7 | I13: =NA() -> #N/A | J13: =B13 -> Neal Stephenson
A14: Delicioso suicidio en grupo | B14: Arto Paasilinna | C14: ebook | D14: 41666 | E14: 41801 | F14: 280 | G14: Novela | H14: 6.5 | I14: =NA() -> #N/A | J14: =B14 -> Arto Paasilinna
A15: El año mil | B15: George Duby | C15: Propio | D15: 41722 | E15: 41737 | F15: 160 | G15: Historia | H15: 1 | I15: =NA() -> #N/A | J15: =B15 -> George Duby
A16: Un mapa en la cabeza | B16: Ken Jennings | C16: Propio | D16: 41737 | E16: 41761 | F16: 344 | G16: Ensayo | H16: 9 | I16: =NA() -> #N/A | J16: =B16 -> Ken Jennings
A17: Crónicas de la mafia | B17: Iñigo Domínguez | C17: Propio | D17: 41763 | E17: 41775 | F17: 431 | G17: Ensayo | H17: 9 | I17: =NA() -> #N/A | J17: =B17 -> Iñigo Domínguez
A18: Amanece que no es poco | B18: Jose Luis Cuerda | C18: Propio | D18: 41775 | E18: 41792 | F18: 312 | G18: Ensayo | H18: 9 | I18: =NA() -> #N/A | J18: =B18 -> Jose Luis Cuerda
A19: Los caminantes | B19: Carlos Sisi | C19: ebook | D19: 41801 | F19: 272 | G19: Novela | I19: =NA() -> #N/A | J19: =B19 -> Carlos Sisi
A20: La última batalla | B20: Eric Hobsbawm | C20: ebook | D20: 41827 | E20: 41871 | F20: 600 | G20: Historia | H20: 7 | I20: =NA() -> #N/A | J20: =B20 -> Eric Hobsbawm
A21: En las antípodas | B21: Bill Bryson | C21: ebook | D21: 41880 | E21: 41886 | F21: 432 | G21: Ensayo | H21: 8 | I21: =NA() -> #N/A | J21: =B21 -> Bill Bryson | K21: 1999
A22: Carlomagno | B22: Harold Lamb | C22: ebook | D22: 41886 | E22: 41899 | F22: 336 | G22: Historia | H22: 6.8 | I22: =NA() -> #N/A | J22: =B22 -> Harold Lamb | K22: 2002
A23: La guerra del Peloponeso | B23: Donald Kagan | C23: ebook | D23: 41899 | E23: 41984 | F23: 768 | G23: Historia | H23: 9 | I23: =NA() -> #N/A | J23: =B23 -> Donald Kagan | K23: 2003
A24: Fundación | B24: Isaac Asimov | C24: ebook | D24: 41984 | E24: 41993 | F24: 230 | G24: Novela | H24: 7 | I24: =NA() -> #N/A | J24: =B24 -> Isaac Asimov | K24: 1951
A25: Fundación e Imperio | B25: Isaac Asimov | C25: ebook | D25: 41993 | E25: 42015 | F25: 320 | G25: Novela | H25: 6.5 | I25: =NA() -> #N/A | J25: =B25 -> Isaac Asimov | K25: 1952
F26: =SUM(F2:F25) -> 8907 | I26: =NA() -> #N/A | J26: =NA() -> #N/A
A27: Estadísticas | I27: =NA() -> #N/A | J27: =NA() -> #N/A
A28: Libros Leídos | B28: Media páginas por libro | C28: Autor más leido | D28: Tipo más leido | I28: =NA() -> #N/A | J28: =NA() -> #N/A
A29: =COUNTIF(E2:E25,">0") -> 12 | B29: =ROUND(F26/A29,0) -> 742 | C29: =INDEX(J2:J53,MATCH(MAX(I2:I53),I2:I53,0),1) -> #N/A | I29: =NA() -> #N/A | J29: =NA() -> #N/A
I30: =NA() -> #N/A | J30: =NA() -> #N/A
I31: =NA() -> #N/A | J31: =NA() -> #N/A
I32: =NA() -> #N/A | J32: =NA() -> #N/A
I33: =NA() -> #N/A | J33: =NA() -> #N/A
I34: =NA() -> #N/A | J34: =NA() -> #N/A
I35: =NA() -> #N/A | J35: =NA() -> #N/A
I36: =NA() -> #N/A | J36: =NA() -> #N/A
I37: =NA() -> #N/A | J37: =NA() -> #N/A
I38: =NA() -> #N/A | J38: =NA() -> #N/A
I39: =NA() -> #N/A | J39: =NA() -> #N/A
I40: =NA() -> #N/A | J40: =NA() -> #N/A
I41: =NA() -> #N/A | J41: =NA() -> #N/A
... I53: =NA() -> #N/A | J53: =NA() -> #N/A

Sheet Leídos 2015
A1: Titulo | B1: Autor | C1: Origen | D1: Fecha Inicio | E1: Fecha Fin | F1: Paginas | G1: Tipo | H1: Puntuación (del 1 al 10) | I1: Num leidos | J1: Autor | K1: Año
A2: Pedro Páramo;El llano en llamas | B2: Juan Rulfo | C2: Prestado | D2: 40150 | F2: 222 | G2: Novela | H2: - | I2: =NA() -> #N/A | J2: =B2 -> Juan Rulfo
A3: Ulises | B3: James Joyce | C3: Propio | D3: 40261 | F3: 910 | G3: Novela | H3: - | I3: =NA() -> #N/A | J3: =B3 -> James Joyce
A4: Diccionario del Diablo | B4: Ambrose Bierce | C4: ebook | D4: 40282 | F4: 480 | G4: Novela | H4: - | I4: =NA() -> #N/A | J4: =B4 -> Ambrose Bierce
A5: Johnny got his gun | B5: Dalton Trumbo | C5: ebook | D5: 40296 | F5: 209 | G5: Novela | H5: - | I5: =NA() -> #N/A | J5: =B5 -> Dalton Trumbo
A6: Nuestras hermanas las ratas | B6: Michel Dansel | C6: ebook | D6: 40366 | F6: 160 | G6: Ensayo | H6: - | I6: =NA() -> #N/A | J6: =B6 -> Michel Dansel
A7: Bolaño salvaje | B7: Varios | C7: Propio | D7: 40373 | F7: 502 | G7: Ensayo | H7: - | I7: =NA() -> #N/A | J7: =B7 -> Varios
A8: Historia de la Inquisición | B8: Primitivo Martínez | C8: ebook | D8: 40385 | F8: 384 | G8: Historia | H8: - | I8: =NA() -> #N/A | J8: =B8 -> Primitivo Martínez
A9: Nuestros orígenes | B9: Richard Leakey | C9: ebook | D9: 40438 | F9: 300 | G9: Antropología | H9: - | I9: =NA() -> #N/A | J9: =B9 -> Richard Leakey
A10: El libro de las ilusiones | B10: Paul Auster | C10: Propio | F10: 338 | G10: Novela | H10: - | I10: =NA() -> #N/A | J10: =B10 -> Paul Auster
A11: La búsqueda de la lengua perfecta | B11: Umberto Eco | C11: ebook | D11: 40655 | F11: 300 | G11: Ensayo | H11: - | I11: =NA() -> #N/A | J11: =B11 -> Umberto Eco
A12: La insurrección que viene | B12: Comité invisible | C12: Propio | D12: 40736 | F12: 144 | G12: Ensayo | H12: - | I12: =NA() -> #N/A | J12: =B12 -> Comité invisible
A13: Los caminantes | B13: Carlos Sisi | C13: ebook | D13: 41801 | F13: 272 | G13: Novela | H13: - | I13: =NA() -> #N/A | J13: =B13 -> Carlos Sisi
A14: Quemando cromo | B14: William Gibson | C14: ebook | D14: 42015 | F14: 232 | G14: Novela | H14: - | I14: =NA() -> #N/A | J14: =B14 -> William Gibson
A15: El marciano | B15: Andy Weir | C15: ebook | D15: 42027 | E15: 42040 | F15: 408 | G15: Novela | H15: 8 | J15: =B15 -> Andy Weir
A16: Verdes valles, colinas rojas 2: Los cuerpos desnudos | B16: Ramiro Pinilla | C16: ebook | D16: 42041 | E16: 42055 | F16: 776 | G16: Novela | H16: 9 | J16: =B16 -> Ramiro Pinilla
A17: Verdes valles, colinas rojas 3: Las cenizas del hierro | B17: Ramiro Pinilla | C17: ebook | D17: 42055 | E17: 42074 | F17: 656 | G17: Novela | H17: 9 | J17: =B17 -> Ramiro Pinilla
A18: La guerra civil española 1 | B18: Hugh Thomas | C18: ebook | D18: 42074 | E18: 42089 | F18: 600 | G18: Historia | H18: 7.5 | J18: =B18 -> Hugh Thomas
A19: La guerra civil española 2 | B19: Hugh Thomas | C19: ebook | D19: 42089 | E19: 42109 | F19: 600 | G19: Historia | H19: 7.5 | J19: =B19 -> Hugh Thomas
A20: El hombre anumérico | B20: John Paulos | C20: ebook | D20: 42109 | E20: 42117 | F20: 216 | G20: Divulgación | H20: 5 | J20: =B20 -> John Paulos
A21: La piel | B21: Curzio Malaparte | C21: ebook | D21: 42117 | E21: 42130 | F21: 400 | G21: Novela | H21: 7.6 | J21: =B21 -> Curzio Malaparte
A22: Crónicas del multiverso | B22: Victor Conde | C22: ebook | D22: 42130 | E22: 42142 | F22: 352 | G22: Novela | H22: 9 | J22: =B22 -> Victor Conde
A23: El disputado voto del señor Cayo | B23: Miguel Delibes | C23: ebook | D23: 42143 | E23: 42149 | F23: 192 | G23: Novela | H23: 7 | J23: =B23 -> Miguel Delibes
A24: Vientos de guerra | B24: Steven Pressfield | C24: ebook | D24: 42149 | E24: 42164 | F24: 528 | G24: Novela | H24: 8 | J24: =B24 -> Steven Pressfield
A25: La sombra del ciprés es alargada | B25: Miguel Delibes | C25: ebook | D25: 42164 | E25: 42173 | F25: 352 | G25: Novela | H25: 5 | J25: =B25 -> Miguel Delibes
A26: A las armas | B26: Quique Peinado | C26: Propio | D26: 42171 | E26: 42174 | F26: 109 | G26: Ensayo | H26: 9 | J26: =B26 -> Quique Peinado
... A34: Límite | B34: Frank Schazting | C34: ebook | D34: 42233 | E34: 42278 | F34: 1376 | G34: Novela | H34: 6 | J34: =B34 -> Frank Schazting
A35: Anatema | B35: Neal Stephenson | C35: Propio | D35: 42241 | F35: 736 | G35: Novela | I35: =NA() -> #N/A | J35: =B35 -> Neal Stephenson
A36: Pistola y cuchillo | B36: Montero González | C36: ebook | D36: 42279 | E36: 42283 | F36: 128 | G36: Novela | H36: 7.6 | I36: =NA() -> #N/A | J36: =B36 -> Montero González
A37: Dientes de gallina y dedos de caballo | B37: Stephen Jay Gould | C37: ebook | D37: 42283 | E37: 42297 | F37: 464 | G37: Divulgación | H37: 5 | I37: =NA() -> #N/A | J37: =B37 -> Stephen Jay Gould | K37: 1983
A38: Crematorio | B38: Rafael Chirbes | C38: ebook | D38: 42297 | E38: 42311 | F38: 424 | G38: Novela | H38: 8 | I38: =NA() -> #N/A | J38: =B38 -> Rafael Chirbes | K38: 2007
A39: La casa de Bernarda Alba | B39: Federico García Lorca | C39: ebook | D39: 42311 | E39: 42313 | F39: 288 | G39: Teatro | H39: 8 | I39: =NA() -> #N/A | J39: =B39 -> Federico García Lorca | K39: 1936
A40: Historia verdadera de la conquista de la Nueva España | B40: Bernar Diaz del Castillo | C40: ebook | D40: 42313 | F40: 1548 | G40: Historia | I40: =NA() -> #N/A | J40: =B40 -> Bernar Diaz del Castillo
A41: Tubos | B41: Andrew Blum | C41: ebook | D41: 42313 | E41: 42325 | F41: 272 | G41: Divulgación | H41: 6 | I41: =NA() -> #N/A | J41: =B41 -> Andrew Blum | K41: 2012
A42: La primera guerra mundial | B42: Martin Gilbert | C42: ebook | D42: 42325 | E42: 42354 | F42: 928 | G42: Historia | H42: 7 | I42: =NA() -> #N/A | J42: =B42 -> Martin Gilbert | K42: 2004
A43: Los santos inocentes | B43: Miguel Delibes | C43: ebook | D43: 42354 | E43: 42357 | F43: 192 | G43: Novela | H43: 8 | I43: =NA() -> #N/A | J43: =B43 -> Miguel Delibes | K43: 1981
F44: =SUMIFS(F2:F43,E2:E43,">0") -> 11891 | H44: =GEOMEAN(H2:H43) -> 7.2003484 | I44: =NA() -> #N/A | J44: =NA() -> #N/A
A45: Estadísticas | I45: =NA() -> #N/A | J45: =NA() -> #N/A
A46: Libros Leídos | B46: Media páginas por libro | C46: Autor más leido | D46: Tipo más leido | I46: =NA() -> #N/A | J46: =NA() -> #N/A
A47: =COUNTIF(E2:E43,">0") -> 27 | B47: =ROUND(F44/A47,0) -> 440 | C47: =INDEX(J2:J71,MATCH(MAX(I2:I71),I2:I71,0),1) -> #N/A | I47: =NA() -> #N/A | J47: =NA() -> #N/A
I48: =NA() -> #N/A | J48: =NA() -> #N/A
I49: =NA() -> #N/A | J49: =NA() -> #N/A
I50: =NA() -> #N/A | J50: =NA() -> #N/A
I51: =NA() -> #N/A | J51: =NA() -> #N/A
I52: =NA() -> #N/A | J52: =NA() -> #N/A
I53: =NA() -> #N/A | J53: =NA() -> #N/A
I54: =NA() -> #N/A | J54: =NA() -> #N/A
I55: =NA() -> #N/A | J55: =NA() -> #N/A
I56: =NA() -> #N/A | J56: =NA() -> #N/A
I57: =NA() -> #N/A | J57: =NA() -> #N/A
I58: =NA() -> #N/A | J58: =NA() -> #N/A
I59: =NA() -> #N/A | J59: =NA() -> #N/A
... I71: =NA() -> #N/A | J71: =NA() -> #N/A

Sheet Leídos 2016
A1: Titulo | B1: Autor | C1: Origen | D1: Fecha Inicio | E1: Fecha Fin | F1: Paginas | G1: Tipo | H1: Puntuación (del 1 al 10) | I1: Num leidos | J1: Autor | K1: Año
A2: Pedro Páramo;El llano en llamas | B2: Juan Rulfo | C2: Prestado | D2: 40150 | F2: 222 | G2: Novela | H2: - | I2: =NA() -> #N/A | J2: =B2 -> Juan Rulfo
A3: Ulises | B3: James Joyce | C3: Propio | D3: 40261 | F3: 910 | G3: Novela | H3: - | I3: =NA() -> #N/A | J3: =B3 -> James Joyce
A4: Diccionario del Diablo | B4: Ambrose Bierce | C4: ebook | D4: 40282 | F4: 480 | G4: Novela | H4: - | I4: =NA() -> #N/A | J4: =B4 -> Ambrose Bierce
A5: Johnny got his gun | B5: Dalton Trumbo | C5: ebook | D5: 40296 | F5: 209 | G5: Novela | H5: - | I5: =NA() -> #N/A | J5: =B5 -> Dalton Trumbo
A6: Nuestras hermanas las ratas | B6: Michel Dansel | C6: ebook | D6: 40366 | F6: 160 | G6: Ensayo | H6: - | I6: =NA() -> #N/A | J6: =B6 -> Michel Dansel
A7: Bolaño salvaje | B7: Varios | C7: Propio | D7: 40373 | F7: 502 | G7: Ensayo | H7: - | I7: =NA() -> #N/A | J7: =B7 -> Varios
A8: Historia de la Inquisición | B8: Primitivo Martínez | C8: ebook | D8: 40385 | F8: 384 | G8: Historia | H8: - | I8: =NA() -> #N/A | J8: =B8 -> Primitivo Martínez
A9: Nuestros orígenes | B9: Richard Leakey | C9: ebook | D9: 40438 | F9: 300 | G9: Antropología | H9: - | I9: =NA() -> #N/A | J9: =B9 -> Richard Leakey
A10: El libro de las ilusiones | B10: Paul Auster | C10: Propio | F10: 338 | G10: Novela | H10: - | I10: =NA() -> #N/A | J10: =B10 -> Paul Auster
A11: La búsqueda de la lengua perfecta | B11: Umberto Eco | C11: ebook | D11: 40655 | F11: 300 | G11: Ensayo | H11: - | I11: =NA() -> #N/A | J11: =B11 -> Umberto Eco
A12: La insurrección que viene | B12: Comité invisible | C12: Propio | D12: 40736 | F12: 144 | G12: Ensayo | H12: - | I12: =NA() -> #N/A | J12: =B12 -> Comité invisible
A13: Los caminantes | B13: Carlos Sisi | C13: ebook | D13: 41801 | F13: 272 | G13: Novela | H13: - | I13: =NA() -> #N/A | J13: =B13 -> Carlos Sisi
A14: Quemando cromo | B14: William Gibson | C14: ebook | D14: 42015 | F14: 232 | G14: Novela | H14: - | I14: =NA() -> #N/A | J14: =B14 -> William Gibson
A15: Hindenburg | B15: Emil Ludwig | C15: ebook | D15: 42357 | E15: 42381 | F15: 560 | G15: Historia | H15: 6 | I15: =NA() -> #N/A | J15: =B15 -> Emil Ludwig | K15: 1935
A16: Rabia | B16: Stephen King | C16: ebook | D16: 42381 | E16: 42386 | F16: 277 | G16: Novela | H16: 7 | J16: =B16 -> Stephen King | K16: 1977
A17: ¿Porqué me comprastéis un walkie-talkie si era hijo único? | B17: Santi Balmes | C17: Propio | D17: 42387 | E17: 42396 | F17: 416 | G17: Novela | H17: 8 | J17: =B17 -> Santi Balmes | K17: 2015
A18: Polvo eres: peripecias y extravagancias de algunos cadaveres inqu ietos | B18: Nieves Concostrina | C18: ebook | D18: 42396 | E18: 42404 | F18: 396 | G18: Historia | H18: 7 | J18: =B18 -> Nieves Concostrina | K18: 2009
A19: La civilización romana | B19: Pierre Grimal | C19: ebook | D19: 42404 | E19: 42422 | F19: 336 | G19: Historia | H19: 7 | J19: =B19 -> Pierre Grimal | K19: 1960
A20: El imperio español: de Colón a Magallanes | B20: Hugh Thomas | C20: ebook | D20: 42422 | E20: 42441 | F20: 800 | G20: Historia | H20: 8 | J20: =B20 -> Hugh Thomas | K20: 2003
A21: HhhH | B21: Laurent Binet | C21: ebook | D21: 42441 | E21: 42451 | F21: 400 | G21: Novela | H21: 7.5 | J21: =B21 -> Laurent Binet | K21: 2011
A22: Fariña | B22: Nacho Carretero | C22: Propio | D22: 42452 | E22: 42459 | F22: 358 | G22: Ensayo | H22: 6.5 | J22: =B22 -> Nacho Carretero | K22: 2015
A23: El Bajo Imperio romano (284-430 d. de C.) | B23: Averil Cameron | C23: ebook | D23: 42457 | E23: 42467 | F23: 240 | G23: Historia | H23: 8.5 | J23: =B23 -> Averil Cameron | K23: 2002
A24: Manual del Perfecto Festivalero | B24: Manuel Bartual | C24: Propio | D24: 42467 | E24: 42473 | F24: 360 | G24: Música | H24: 9 | J24: =B24 -> Manuel Bartual | K24: 2015
A25: Ojo en el cielo | B25: Philip K.Dick | C25: ebook | D25: 42474 | E25: 42481 | F25: 292 | G25: Novela | H25: 6.5 | J25: =B25 -> Philip K.Dick | K25: 1957
A26: 091: aullidos, corazones y guitarras | B26: Juan Jesús García | C26: Propio | D26: 42481 | E26: 42488 | F26: 192 | G26: Música | H26: 8.75 | J26: =B26 -> Juan Jesús García | K26: 2016
A27: Monsieur Pain | B27: Roberto Bolaño | C27: ebook | D27: 42488 | E27: 42496 | F27: 176 | G27: Novela | H27: 7 | J27: =B27 -> Roberto Bolaño | K27: 1999
... A39: La cruzada del sur | B39: Juan Antonio Cebrian | C39: ebook | D39: 42595 | E39: 42601 | F39: 256 | G39: Historia | H39: 5 | J39: =B39 -> Juan Antonio Cebrian | K39: 2003
A40: Mystes | B40: Victor Conde | C40: ebook | D40: 42601 | E40: 42602 | F40: 224 | G40: Novela | H40: 6 | K40: 2004
A41: Plenilunio | B41: Antonio Muñoz Molina | C41: ebook | D41: 42602 | E41: 42616 | F41: 384 | G41: Novela | H41: 7 | K41: 1997
A42: Seveneves | B42: Neal Stephenson | C42: ebook | D42: 42616 | E42: 42626 | F42: 816 | G42: Novela | H42: 9 | K42: 2016
A43: Temerario I. El dragón de su majestad | B43: Naomi Novik | C43: ebook | D43: 42626 | E43: 42632 | F43: 416 | G43: Novela | H43: 7 | K43: 2006
A44: El ojo del mundo | B44: Robert Jordan | C44: ebook | D44: 42632 | E44: 42653 | F44: 640 | G44: Novela | H44: 8.5 | K44: 1990
A45: SPQR | B45: Mary Beard | C45: ebook | D45: 42653 | E45: 42669 | F45: 664 | G45: Historia | H45: 8.9 | K45: 2016
A46: Roma eterna | B46: Robert Silverberg | C46: ebook | D46: 42669 | E46: 42682 | F46: 400 | G46: Novela | H46: 7 | K46: 2003
A47: 1927: un verano que cambió el mundo | B47: Bill Bryson | C47: ebook | D47: 42682 | E47: 42693 | F47: 624 | G47: Divulgación | H47: 8 | K47: 2015
A48: El despertar de los héroes | B48: Robert Jordan | C48: ebook | D48: 42694 | E48: 42718 | F48: 558 | G48: Novela | H48: 8 | K48: 1991
A49: Cosas que los nietos deberían saber | B49: Mark Oliver Everett | C49: ebook | D49: 42718 | E49: 42721 | F49: 224 | G49: Biografía | H49: 7.9 | K49: 2009
F50: =SUMIFS(F2:F45,E2:E45,">0") -> 13222 | H50: =GEOMEAN(H2:H45) -> 7.1305769 | I50: =NA() -> #N/A | J50: =NA() -> #N/A
A51: Estadísticas | I51: =NA() -> #N/A | J51: =NA() -> #N/A
A52: Libros Leídos | B52: Media páginas por libro | C52: Autor más leido | D52: Tipo más leido | I52: =NA() -> #N/A | J52: =NA() -> #N/A
A53: =COUNTIF(E2:E49,">0") -> 35 | B53: =ROUND(F50/A53,0) -> 378 | C53: =INDEX(J2:J77,MATCH(MAX(I2:I77),I2:I77,0),1) -> #N/A | I53: =NA() -> #N/A | J53: =NA() -> #N/A
I54: =NA() -> #N/A | J54: =NA() -> #N/A
I55: =NA() -> #N/A | J55: =NA() -> #N/A
I56: =NA() -> #N/A | J56: =NA() -> #N/A
A57: Un ejercito al amanecer | B57: Rick Atkinson | C57: ebook | D57: 40702 | E57: 40721 | F57: 672 | G57: Historia | H57: 6.5 | I57: =NA() -> #N/A | J57: =B57 -> Rick Atkinson
I58: =NA() -> #N/A | J58: =NA() -> #N/A
I59: =NA() -> #N/A | J59: =NA() -> #N/A
I60: =NA() -> #N/A | J60: =NA() -> #N/A
I61: =NA() -> #N/A | J61: =NA() -> #N/A
I62: =NA() -> #N/A | J62: =NA() -> #N/A
I63: =NA() -> #N/A | J63: =NA() -> #N/A
I64: =NA() -> #N/A | J64: =NA() -> #N/A
I65: =NA() -> #N/A | J65: =NA() -> #N/A
I66: =NA() -> #N/A | J66: =NA() -> #N/A
I67: =NA() -> #N/A | J67: =NA() -> #N/A
I68: =NA() -> #N/A | J68: =NA() -> #N/A
I69: =NA() -> #N/A | J69: =NA() -> #N/A
... I77: =NA() -> #N/A | J77: =NA() -> #N/A

Sheet Leídos 2017
A1: Titulo | B1: Autor | C1: Origen | D1: Fecha Inicio | E1: Fecha Fin | F1: Paginas | G1: Tipo | H1: Puntuación (del 1 al 10) | I1: Num leidos | J1: Autor | K1: Año
A2: Pedro Páramo;El llano en llamas | B2: Juan Rulfo | C2: Prestado | D2: 40150 | F2: 222 | G2: Novela | H2: - | I2: =NA() -> #N/A | J2: =B2 -> Juan Rulfo
A3: Ulises | B3: James Joyce | C3: Propio | D3: 40261 | F3: 910 | G3: Novela | H3: - | I3: =NA() -> #N/A | J3: =B3 -> James Joyce
A4: Diccionario del Diablo | B4: Ambrose Bierce | C4: ebook | D4: 40282 | F4: 480 | G4: Novela | H4: - | I4: =NA() -> #N/A | J4: =B4 -> Ambrose Bierce
A5: Johnny got his gun | B5: Dalton Trumbo | C5: ebook | D5: 40296 | F5: 209 | G5: Novela | H5: - | I5: =NA() -> #N/A | J5: =B5 -> Dalton Trumbo
A6: Nuestras hermanas las ratas | B6: Michel Dansel | C6: ebook | D6: 40366 | F6: 160 | G6: Ensayo | H6: - | I6: =NA() -> #N/A | J6: =B6 -> Michel Dansel
A7: Bolaño salvaje | B7: Varios | C7: Propio | D7: 40373 | F7: 502 | G7: Ensayo | H7: - | I7: =NA() -> #N/A | J7: =B7 -> Varios
A8: Historia de la Inquisición | B8: Primitivo Martínez | C8: ebook | D8: 40385 | F8: 384 | G8: Historia | H8: - | I8: =NA() -> #N/A | J8: =B8 -> Primitivo Martínez
A9: Nuestros orígenes | B9: Richard Leakey | C9: ebook | D9: 40438 | F9: 300 | G9: Antropología | H9: - | I9: =NA() -> #N/A | J9: =B9 -> Richard Leakey
A10: El libro de las ilusiones | B10: Paul Auster | C10: Propio | F10: 338 | G10: Novela | H10: - | I10: =NA() -> #N/A | J10: =B10 -> Paul Auster
A11: La búsqueda de la lengua perfecta | B11: Umberto Eco | C11: ebook | D11: 40655 | F11: 300 | G11: Ensayo | H11: - | I11: =NA() -> #N/A | J11: =B11 -> Umberto Eco
A12: La insurrección que viene | B12: Comité invisible | C12: Propio | D12: 40736 | F12: 144 | G12: Ensayo | H12: - | I12: =NA() -> #N/A | J12: =B12 -> Comité invisible
A13: Los caminantes | B13: Carlos Sisi | C13: ebook | D13: 41801 | F13: 272 | G13: Novela | H13: - | I13: =NA() -> #N/A | J13: =B13 -> Carlos Sisi
A14: Quemando cromo | B14: William Gibson | C14: ebook | D14: 42015 | F14: 232 | G14: Novela | H14: - | I14: =NA() -> #N/A | J14: =B14 -> William Gibson
A15: 1914: de la paz a la guerra | B15: Margaret Macmillan | C15: ebook | D15: 42722 | E15: 42746 | F15: 864 | G15: Historia | H15: 8 | K15: 2016
A16: Nocturno de Chile | B16: Roberto Bolaño | C16: ebook | D16: 42746 | E16: 42748 | F16: 152 | G16: Novela | H16: 8 | I16: =NA() -> #N/A | J16: =B16 -> Roberto Bolaño | K16: 2000
A17: Metro 2033 | B17: Dmitri Glujovski | C17: ebook | D17: 42748 | E17: 42768 | F17: 544 | G17: Novela | H17: 6 | I17: =NA() -> #N/A | J17: =B17 -> Dmitri Glujovski | K17: 2007
A18: Ojos de fuego | B18: Stephen King | C18: ebook | D18: 42768 | E18: 42783 | F18: 592 | G18: Novela | H18: 6 | I18: =NA() -> #N/A | J18: =B18 -> Stephen King | K18: 1980
A19: Tres días y una vida | B19: Pierre Lemaitre | C19: ebook | D19: 42784 | E19: 42795 | F19: 224 | G19: Novela | H19: 7 | I19: =NA() -> #N/A | J19: =B19 -> Pierre Lemaitre | K19: 2016
A20: Sapiens, de animales a dioses | B20: Yuval Noah Harari | C20: ebook | D20: 42796 | E20: 42807 | F20: 496 | G20: Ensayo | H20: 8 | I20: =NA() -> #N/A | J20: =B20 -> Yuval Noah Harari | K20: 2014
A21: Armagedon: la derrota de Alemania | B21: Max Hastings | C21: ebook | D21: 42807 | E21: 42842 | F21: 856 | G21: Historia | H21: 7 | I21: =NA() -> #N/A | J21: =B21 -> Max Hastings | K21: 2005
A22: El dragón renacido | B22: Robert Jordan | C22: ebook | D22: 42842 | E22: 42864 | F22: 512 | G22: Novela | H22: 7.5 | I22: =NA() -> #N/A | J22: =B22 -> Robert Jordan | K22: 1991
A23: El aumento de la sombra | B23: Robert Jordan | C23: ebook | D23: 42864 | E23: 42886 | F23: 1013 | G23: Novela | H23: 7.6 | I23: =NA() -> #N/A | J23: =B23 -> Robert Jordan | K23: 1992
A24: Las lagartijas no se hacen preguntas | B24: Leonard Mlodinow | C24: ebook | D24: 42886 | E24: 42891 | F24: 416 | G24: Divulgación | H24: 9 | I24: =NA() -> #N/A | J24: =B24 -> Leonard Mlodinow | K24: 2016
A25: Huevo del dragón (cheela 1) | B25: Robert L. Forward | C25: ebook | D25: 42891 | E25: 42899 | F25: 330 | G25: Novela | H25: 6 | I25: =NA() -> #N/A | J25: =B25 -> Robert L. Forward | K25: 1980
A26: Don Quijote de la Mancha | B26: Miguel de Cervantes Saavedra | C26: ebook | D26: 42897 | F26: 573 | G26: Novela | I26: =NA() -> #N/A | J26: =B26 -> Miguel de Cervantes Saavedra | K26: 1605
A27: El atlas de las nubes | B27: David Mitchell | C27: ebook | D27: 42899 | E27: 42909 | F27: 608 | G27: Novela | H27: 8 | I27: =NA() -> #N/A | J27: =B27 -> David Mitchell | K27: 2004
A28: El sueño de Galileo | B28: Kim Stanley Robinson | C28: ebook | D28: 42910 | E28: 42919 | F28: 544 | G28: Novela | H28: 6 | I28: =NA() -> #N/A | J28: =B28 -> Kim Stanley Robinson | K28: 2010
A29: Moby Dick | B29: Herman Melville | C29: ebook | D29: 42920 | E29: 42943 | F29: 544 | G29: Novela | H29: 6 | I29: =NA() -> #N/A | J29: =B29 -> Herman Melville | K29: 1860
A30: El cielo en llamas | B30: Robert Jordan | C30: ebook | D30: 42943 | E30: 42970 | F30: 512 | G30: Novela | H30: 6.5 | I30: =NA() -> #N/A | J30: =B30 -> Robert Jordan | K30: 1993
A31: La torre oscura 1: el pistolero | B31: Stephen King | C31: ebook | D31: 42970 | E31: 42974 | F31: 236 | G31: Novela | H31: 6 | I31: =NA() -> #N/A | J31: =B31 -> Stephen King | K31: 1982
A32: 2312 | B32: Kim Stanley Robinson | C32: ebook | D32: 42974 | E32: 42985 | F32: 528 | G32: Novela | H32: 4.5 | I32: =NA() -> #N/A | J32: =B32 -> Kim Stanley Robinson | K32: 2012
A33: Ritos iguales | B33: Terry Pratchett | C33: ebook | D33: 42987 | E33: 42993 | F33: 272 | G33: Novela | H33: 8 | I33: =NA() -> #N/A | J33: =B33 -> Terry Pratchett | K33: 1987
A34: Homo deus | B34: Yuval Noah Harari | C34: ebook | D34: 42993 | E34: 43007 | F34: 496 | G34: Ensayo | H34: 8.5 | I34: =NA() -> #N/A | J34: =B34 -> Yuval Noah Harari | K34: 2015
A35: Brujerías | B35: Terry Pratchett | C35: ebook | D35: 43007 | E35: 43019 | F35: 328 | G35: Novela | H35: 8.5 | I35: =NA() -> #N/A | J35: =B35 -> Terry Pratchett | K35: 1992
A36: La guerra secreta 1939-1945 | B36: Max Hastings | C36: ebook | D36: 43019 | E36: 43046 | F36: 824 | G36: Ensayo | H36: 7.5 | I36: =NA() -> #N/A | J36: =B36 -> Max Hastings | K36: 2016
A37: Miles Vorkosigan IV - El aprendiz del guerrero | B37: Lois McMaster Bujold | C37: ebook | D37: 43046 | E37: 43062 | F37: 432 | G37: Novela | H37: 7.9 | I37: =NA() -> #N/A | J37: =B37 -> Lois McMaster Bujold | K37: 1986
A38: Miles Vorkosigan V - Fronteras del infinito | B38: Lois McMaster Bujold | C38: ebook | D38: 43062 | E38: 43067 | F38: 384 | G38: Novela | H38: 8.5 | I38: =NA() -> #N/A | J38: =B38 -> Lois McMaster Bujold | K38: 1989
A39: Miles Vorkosigan VI - El juego de los Vor | B39: Lois McMaster Bujold | C39: ebook | D39: 43067 | E39: 43076 | F39: 448 | G39: Novela | H39: 8 | I39: =NA() -> #N/A | J39: =B39 -> Lois McMaster Bujold | K39: 1990
A40: Chavs: la demonización de la clase obrera | B40: Owen Jones | C40: ebook | D40: 43076 | E40: 43086 | F40: 360 | G40: Ensayo | H40: 4 | I40: =NA() -> #N/A | J40: =B40 -> Owen Jones | K40: 2011
A41: Miles Vorkosigan VII - Cetaganda | B41: Lois McMaster Bujold | C41: ebook | D41: 43086 | E41: 43100 | F41: 384 | G41: Novela | H41: 6 | I41: =NA() -> #N/A | J41: =B41 -> Lois McMaster Bujold | K41: 1995
F42: =SUMIFS(F2:F41,E2:E41,">0") -> 12899 | H42: =GEOMEAN(H2:H41) -> 6.9521165 | I42: =NA() -> #N/A | J42: =NA() -> #N/A
A43: Estadísticas | I43: =NA() -> #N/A | J43: =NA() -> #N/A
A44: Libros Leídos | B44: Media páginas por libro | C44: Autor más leido | D44: Tipo más leido | I44: =NA() -> #N/A | J44: =NA() -> #N/A
A45: =COUNTIF(E2:E41,">0") -> 26 | B45: =ROUND(F42/A45,0) -> 496 | C45: =INDEX(J2:J69,MATCH(MAX(I2:I69),I2:I69,0),1) -> #N/A | I45: =NA() -> #N/A | J45: =NA() -> #N/A
I46: =NA() -> #N/A | J46: =NA() -> #N/A
I47: =NA() -> #N/A | J47: =NA() -> #N/A
I48: =NA() -> #N/A | J48: =NA() -> #N/A
A49: Un ejercito al amanecer | B49: Rick Atkinson | C49: ebook | D49: 40702 | E49: 40721 | F49: 672 | G49: Historia | H49: 6.5 | I49: =NA() -> #N/A | J49: =B49 -> Rick Atkinson
I50: =NA() -> #N/A | J50: =NA() -> #N/A
I51: =NA() -> #N/A | J51: =NA() -> #N/A
I52: =NA() -> #N/A | J52: =NA() -> #N/A
I53: =NA() -> #N/A | J53: =NA() -> #N/A
I54: =NA() -> #N/A | J54: =NA() -> #N/A
I55: =NA() -> #N/A | J55: =NA() -> #N/A
I56: =NA() -> #N/A | J56: =NA() -> #N/A
I57: =NA() -> #N/A | J57: =NA() -> #N/A
I58: =NA() -> #N/A | J58: =NA() -> #N/A
I59: =NA() -> #N/A | J59: =NA() -> #N/A
I60: =NA() -> #N/A | J60: =NA() -> #N/A
I61: =NA() -> #N/A | J61: =NA() -> #N/A
... I69: =NA() -> #N/A | J69: =NA() -> #N/A

Sheet Leídos 2018
A1: Titulo | B1: Autor | C1: Origen | D1: Fecha Inicio | E1: Fecha Fin | F1: Paginas | G1: Tipo | H1: Puntuación (del 1 al 10) | I1: Num leidos | J1: Autor | K1: Año
A2: Pedro Páramo;El llano en llamas | B2: Juan Rulfo | C2: Prestado | D2: 40150 | F2: 222 | G2: Novela | H2: - | I2: =NA() -> #N/A | J2: =B2 -> Juan Rulfo
A3: Ulises | B3: James Joyce | C3: Propio | D3: 40261 | F3: 910 | G3: Novela | H3: - | I3: =NA() -> #N/A | J3: =B3 -> James Joyce
A4: Diccionario del Diablo | B4: Ambrose Bierce | C4: ebook | D4: 40282 | F4: 480 | G4: Novela | H4: - | I4: =NA() -> #N/A | J4: =B4 -> Ambrose Bierce
A5: Johnny got his gun | B5: Dalton Trumbo | C5: ebook | D5: 40296 | F5: 209 | G5: Novela | H5: - | I5: =NA() -> #N/A | J5: =B5 -> Dalton Trumbo
A6: Nuestras hermanas las ratas | B6: Michel Dansel | C6: ebook | D6: 40366 | F6: 160 | G6: Ensayo | H6: - | I6: =NA() -> #N/A | J6: =B6 -> Michel Dansel
A7: Bolaño salvaje | B7: Varios | C7: Propio | D7: 40373 | F7: 502 | G7: Ensayo | H7: - | I7: =NA() -> #N/A | J7: =B7 -> Varios
A8: Historia de la Inquisición | B8: Primitivo Martínez | C8: ebook | D8: 40385 | F8: 384 | G8: Historia | H8: - | I8: =NA() -> #N/A | J8: =B8 -> Primitivo Martínez
A9: Nuestros orígenes | B9: Richard Leakey | C9: ebook | D9: 40438 | F9: 300 | G9: Antropología | H9: - | I9: =NA() -> #N/A | J9: =B9 -> Richard Leakey
A10: El libro de las ilusiones | B10: Paul Auster | C10: Propio | F10: 338 | G10: Novela | H10: - | I10: =NA() -> #N/A | J10: =B10 -> Paul Auster
A11: La búsqueda de la lengua perfecta | B11: Umberto Eco | C11: ebook | D11: 40655 | F11: 300 | G11: Ensayo | H11: - | I11: =NA() -> #N/A | J11: =B11 -> Umberto Eco
A12: La insurrección que viene | B12: Comité invisible | C12: Propio | D12: 40736 | F12: 144 | G12: Ensayo | H12: - | I12: =NA() -> #N/A | J12: =B12 -> Comité invisible
A13: Los caminantes | B13: Carlos Sisi | C13: ebook | D13: 41801 | F13: 272 | G13: Novela | H13: - | I13: =NA() -> #N/A | J13: =B13 -> Carlos Sisi
A14: Quemando cromo | B14: William Gibson | C14: ebook | D14: 42015 | F14: 232 | G14: Novela | H14: - | I14: =NA() -> #N/A | J14: =B14 -> William Gibson
A15: Don Quijote de la Mancha | B15: Miguel de Cervantes Saavedra | C15: ebook | D15: 42897 | E15: 43200 | F15: 573 | G15: Novela | H15: 8 | I15: =NA() -> #N/A | J15: =B15 -> Miguel de Cervantes Saavedra | K15: 1605
A16: ¡Guardias! ¿Guardias? | B16: Terry Pratchett | C16: ebook | D16: 43100 | E16: 43119 | F16: 400 | G16: Novela | H16: 8 | K16: 1993
A17: Historia inventada del punk | B17: Juarma / Jorge B. Ortiz | C17: Propio | D17: 43105 | E17: 43105 | F17: 40 | G17: Comic | H17: 8 | K17: 2017
A18: Cuatro millones de golpes | B18: Erik Jimenez | C18: Propio | D18: 43105 | E18: 43114 | F18: 288 | G18: Biografía | H18: 7 | K18: 2017
A19: Prohibido Nacer | B19: Trevor Noah | C19: Propio | D19: 43115 | E19: 43242 | F19: 328 | G19: Biografía | H19: 6 | K19: 2017
A20: Hombres de armas | B20: Terry Pratchett | C20: ebook | D20: 43119 | E20: 43142 | F20: 352 | G20: Novela | H20: 8 | K20: 1993
A21: Pies de barro | B21: Terry Pratchett | C21: ebook | D21: 43143 | E21: 43159 | F21: 368 | G21: Novela | H21: 8.5 | K21: 1996
A22: !Voto a bríos! | B22: Terry Pratchett | C22: ebook | D22: 43160 | E22: 43169 | F22: 400 | G22: Novela | H22: 9 | K22: 1997
A23: La amiga estupenda | B23: Elena Ferrante | C23: ebook | D23: 43169 | E23: 43182 | F23: 392 | G23: Novela | H23: 8 | K23: 2011
A24: (Ekumen 2) Planeta de exilio | B24: Ursula K. Le Guin | C24: ebook | D24: 43200 | E24: 43206 | F24: 224 | G24: Novela | H24: 7.8 | K24: 1966
A25: Aurora | B25: Kim Stanley Robinson | C25: ebook | D25: 43206 | E25: 43224 | F25: 448 | G25: Novela | H25: 7 | K25: 2015
A26: Manual de Historia medieval | B26: Jose Angel Sesma Muñoz y Jose Angel García de Cortazar | C26: ebook | D26: 43224 | E26: 43258 | F26: 584 | G26: Historia | H26: 7.5 | K26: 2015
A27: La historia del Heavy Metal | B27: Andrew O´Neil | C27: Propio | D27: 43229 | E27: 43233 | F27: 352 | G27: Historia | H27: 9 | K27: 2018
... A31: La gente de la edad media | B31: Robert Fossier | C31: ebook | D31: 43280 | E31: 43296 | F31: 392 | G31: Historia | H31: 7 | K31: 2007
A32: Miles Vorkosigan VIII - Ethan de Athos | B32: Lois McMaster Bujold | C32: ebook | D32: 43297 | E32: 43299 | F32: 224 | G32: Novela | H32: 7.5 | I32: =NA() -> #N/A | J32: =B32 -> Lois McMaster Bujold | K32: 1986
A33: Miles Vorkosigan IX - Hermanos de armas | B33: Lois McMaster Bujold | C33: ebook | D33: 43299 | E33: 43301 | F33: 400 | G33: Novela | H33: 7.3 | K33: 1989
A34: Cinco ecuaciones que cambiaron el mundo | B34: Michael Guillen | C34: ebook | D34: 43302 | E34: 43303 | F34: 288 | G34: Ensayo | H34: 7 | K34: 1995
A35: Ciudad Permutación | B35: Greg Egan | C35: ebook | D35: 43303 | E35: 43316 | F35: 416 | G35: Novela | H35: 6 | K35: 1994
A36: (Ekumen 3) La ciudad de las ilusiones | B36: Ursula K. Le Guin | C36: ebook | D36: 43297 | E36: 43318 | F36: 256 | G36: Novela | H36: 8 | K36: 1967
A37: La partícula divina | B37: Leon Max Lederman | C37: ebook | D37: 43309 | E37: 43329 | F37: 616 | G37: Ensayo | H37: 8 | K37: 1993
A38: Nemesis: la derrota de Japón 1944-1945 | B38: Max Hastings | C38: ebook | D38: 43329 | E38: 43361 | F38: 880 | G38: Historia | H38: 9 | K38: 2008
A39: El estado de las cosas | B39: Roberto Herreros / Isidro Lopez | C39: Propio | D39: 43354 | E39: 43371 | F39: 226 | G39: Música | H39: 7 | K39: 2018
A40: El bosque oscuro | B40: Liu Cixin | C40: ebook | D40: 43362 | E40: 43401 | F40: 600 | G40: Novela | H40: 8 | K40: 2008
A41: El misterio de la orquídea calavera | B41: Elmer Mendoza | C41: ebook | D41: 43401 | E41: 43412 | F41: 296 | G41: Novela | H41: 9 | K41: 2014
A42: Nacidos de la bruma 1: El imperio final | B42: Brandon Sanderson | C42: ebook | D42: 43412 | E42: 43435 | F42: 688 | G42: Novela | H42: 9 | K42: 2006
A43: Nacidos de la bruma 2: El pozo de la ascensión | B43: Brandon Sanderson | C43: ebook | D43: 43435 | E43: 43465 | F43: 800 | G43: Novela | H43: 9 | K43: 2007
F44: =SUMIFS(F2:F43,E2:E43,">0") -> 11755 | H44: =GEOMEAN(H2:H43) -> 7.789367 | I44: =NA() -> #N/A | J44: =NA() -> #N/A
A45: Estadísticas | I45: =NA() -> #N/A | J45: =NA() -> #N/A
A46: Libros Leídos | B46: Media páginas por libro | C46: Autor más leido | D46: Tipo más leido | I46: =NA() -> #N/A | J46: =NA() -> #N/A
A47: =COUNTIF(E2:E43,">0") -> 29 | B47: =ROUND(F44/A47,0) -> 405 | C47: =INDEX(J2:J71,MATCH(MAX(I2:I71),I2:I71,0),1) -> #N/A | I47: =NA() -> #N/A | J47: =NA() -> #N/A
I48: =NA() -> #N/A | J48: =NA() -> #N/A
I49: =NA() -> #N/A | J49: =NA() -> #N/A
I50: =NA() -> #N/A | J50: =NA() -> #N/A
A51: Un ejercito al amanecer | B51: Rick Atkinson | C51: ebook | D51: 40702 | E51: 40721 | F51: 672 | G51: Historia | H51: 6.5 | I51: =NA() -> #N/A | J51: =B51 -> Rick Atkinson
I52: =NA() -> #N/A | J52: =NA() -> #N/A
I53: =NA() -> #N/A | J53: =NA() -> #N/A
I54: =NA() -> #N/A | J54: =NA() -> #N/A
I55: =NA() -> #N/A | J55: =NA() -> #N/A
I56: =NA() -> #N/A | J56: =NA() -> #N/A
I57: =NA() -> #N/A | J57: =NA() -> #N/A
I58: =NA() -> #N/A | J58: =NA() -> #N/A
I59: =NA() -> #N/A | J59: =NA() -> #N/A
I60: =NA() -> #N/A | J60: =NA() -> #N/A
I61: =NA() -> #N/A | J61: =NA() -> #N/A
I62: =NA() -> #N/A | J62: =NA() -> #N/A
I63: =NA() -> #N/A | J63: =NA() -> #N/A
... I71: =NA() -> #N/A | J71: =NA() -> #N/A

Sheet Leídos 2019
A1: Titulo | B1: Autor | C1: Origen | D1: Fecha Inicio | E1: Fecha Fin | F1: Paginas | G1: Tipo | H1: Puntuación (del 1 al 10) | I1: Num leidos | J1: Autor | K1: Año
A2: (Ekumen 4) La mano izquierda de la oscuridad | B2: Ursula K. Le Guin | C2: ebook | D2: 43318 | F2: 304 | G2: Novela | K2: 1969
A3: La sustancia del mal | B3: Luca D. Andrea | C3: Prestado | D3: 43372 | F3: 472 | G3: Novela | K3: 2016
A4: El fin de la muerte | B4: Liu Cixin | C4: ebook | D4: 43466 | E4: 43490 | F4: 736 | G4: Novela | H4: 8 | K4: 2008
A5: Un ascensor al espacio | B5: Kelly y Zach Weinersmith | C5: Propio | D5: 43469 | E5: 43585 | F5: 480 | G5: Ciencia | H5: 8 | K5: 2018
A6: El señor del caos | B6: Robert Jordan | C6: ebook | D6: 43490 | E6: 43574 | F6: 560 | G6: Novela | H6: 8 | K6: 1994
A7: Poema del mio Cid | B7: Anonimo | C7: Prestado | D7: 43497 | E7: 43532 | F7: 336 | G7: Poema | H7: 8 | K7: 1152
A8: Ciudad Abismo | B8: Alastair Reynolds | C8: ebook | D8: 43575 | E8: 43609 | F8: 512 | G8: Novela | H8: 9 | K8: 2001
A9: Nacer Crecer Metallica Morir Tomo 1 | B9: Paul Brannigan | C9: Propio | D9: 43590 | E9: 43600 | F9: 400 | G9: Música | H9: 8 | K9: 2018
A10: Los desnudos y los muertos | B10: Norman Mailer | C10: Propio | D10: 43601 | E10: 43737 | F10: 721 | G10: Novela | H10: 8 | K10: 1948
A11: Buenos presagios | B11: Neil Gaiman y Terry Pratchett | C11: ebook | D11: 43609 | E11: 43623 | F11: 352 | G11: Novela | H11: 8.7 | K11: 1990
A12: El prefecto | B12: Alastair Reynolds | C12: ebook | D12: 43623 | E12: 43637 | F12: 416 | G12: Novela | H12: 8.5 | K12: 2007
A13: El arca de la redención | B13: Alastair Reynolds | C13: ebook | D13: 43637 | E13: 43666 | F13: 608 | G13: Novela | H13: 8 | K13: 2002
A14: La quinta estación | B14: N. K. Jemisin | C14: ebook | D14: 43666 | E14: 43694 | F14: 448 | G14: Novela | H14: 8 | K14: 2015
A15: Marvel Classic La odisea | B15: Roy Thomas, Greg Tocchini | C15: Propio | D15: 43673 | E15: 43673 | F15: 200 | G15: Comic | H15: 8 | K15: 2013
... A22: Miles Vorkosigan X - Danza de espejos | B22: Lois McMaster Bujold | C22: ebook | D22: 43784 | E22: 43800 | F22: 507 | G22: Novela | H22: 8 | K22: 1995
A23: La extraordinaria familia Telemacus | B23: Daryl Gregory | C23: Propio | D23: 43790 | F23: 416 | G23: Novela | K23: 2017
A24: Miles Vorkosigan XI - Recuerdos | B24: Lois McMaster Bujold | C24: ebook | D24: 43800 | E24: 43806 | F24: 608 | G24: Novela | H24: 8 | K24: 1997
A25: Miles Vorkosigan XII - Komarr | B25: Lois McMaster Bujold | C25: ebook | D25: 43806 | E25: 43814 | F25: 352 | G25: Novela | H25: 8 | K25: 1998
A26: El desfiladero de la absolución | B26: Alastair Reynolds | C26: ebook | D26: 43814 | E26: 43830 | F26: 640 | G26: Novela | H26: 7 | K26: 2003
F27: =SUMIFS(F2:F26,E2:E26,">0") -> 10870 | H27: =GEOMEAN(H4:H26) -> 8.0060097 | I27: =NA() -> #N/A | J27: =NA() -> #N/A
A28: Estadísticas | I28: =NA() -> #N/A | J28: =NA() -> #N/A
A29: Libros Leídos | B29: Media páginas por libro | C29: Autor más leido | D29: Tipo más leido | I29: =NA() -> #N/A | J29: =NA() -> #N/A
A30: =COUNTIF(E2:E26,">0") -> 22 | B30: =ROUND(F27/A30,0) -> 494 | C30: =INDEX(J4:J54,MATCH(MAX(I4:I54),I4:I54,0),1) -> #N/A | I30: =NA() -> #N/A | J30: =NA() -> #N/A
I31: =NA() -> #N/A | J31: =NA() -> #N/A
I32: =NA() -> #N/A | J32: =NA() -> #N/A
I33: =NA() -> #N/A | J33: =NA() -> #N/A
A34: Un ejercito al amanecer | B34: Rick Atkinson | C34: ebook | D34: 40702 | E34: 40721 | F34: 672 | G34: Historia | H34: 6.5 | I34: =NA() -> #N/A | J34: =B34 -> Rick Atkinson
I35: =NA() -> #N/A | J35: =NA() -> #N/A
I36: =NA() -> #N/A | J36: =NA() -> #N/A
I37: =NA() -> #N/A | J37: =NA() -> #N/A
I38: =NA() -> #N/A | J38: =NA() -> #N/A
I39: =NA() -> #N/A | J39: =NA() -> #N/A
I40: =NA() -> #N/A | J40: =NA() -> #N/A
I41: =NA() -> #N/A | J41: =NA() -> #N/A
I42: =NA() -> #N/A | J42: =NA() -> #N/A
I43: =NA() -> #N/A | J43: =NA() -> #N/A
I44: =NA() -> #N/A | J44: =NA() -> #N/A
I45: =NA() -> #N/A | J45: =NA() -> #N/A
I46: =NA() -> #N/A | J46: =NA() -> #N/A
... I54: =NA() -> #N/A | J54: =NA() -> #N/A

Sheet Leídos 2020
A1: Titulo | B1: Autor | C1: Origen | D1: Fecha Inicio | E1: Fecha Fin | F1: Paginas | G1: Tipo | H1: Puntuación (del 1 al 10) | I1: Num leidos | J1: Autor | K1: Año
A2: (Ekumen 4) La mano izquierda de la oscuridad | B2: Ursula K. Le Guin | C2: ebook | D2: 43318 | F2: 304 | G2: Novela | K2: 1969
A3: La sustancia del mal | B3: Luca D. Andrea | C3: Prestado | D3: 43372 | E3: 43997 | F3: 472 | G3: Novela | H3: 0 | K3: 2016
A4: La extraordinaria familia Telemacus | B4: Daryl Gregory | C4: Propio | D4: 43790 | E4: 44150 | F4: 416 | G4: Novela | H4: 0 | K4: 2017
A5: Los jardines de la Luna (Malaz: El Libro de los Caídos 1) | B5: Steven Erikson | C5: ebook | D5: 43830 | E5: 43860 | F5: 768 | G5: Novela | H5: 8 | K5: 1999
A6: Las puertas de la Casa de la Muerte (Malaz: El Libro de los Caídos 2) | B6: Steven Erikson | C6: ebook | D6: 43860 | E6: 43889 | F6: 943 | G6: Novela | H6: 8 | K6: 2000
A7: Hijos de una guerra: Los Hermanos Quero y la resistencia antifranquista | B7: Jorge Marco Carretero | C7: Propio | D7: 43870 | E7: 43884 | F7: 448 | G7: Historia | H7: 9 | K7: 2019
A8: Memorias del Hielo (Malaz: El Libro de los Caídos 3) | B8: Steven Erikson | C8: ebook | D8: 43889 | E8: 44185 | F8: 1184 | G8: Novela | H8: 7 | K8: 2001
A9: 14 de Julio | B9: Eric Villard | C9: ebook | D9: 43908 | E9: 43916 | F9: 192 | G9: Historia | H9: 3 | K9: 2016
A10: Fariña, la novela gráfica | B10: Luis Bustos | C10: Propio | D10: 43909 | E10: 43912 | F10: 128 | G10: Historieta | H10: 8.5 | K10: 2020
A11: Diario del año de la peste | B11: Daniel Defoe | C11: ebook | D11: 43916 | E11: 43936 | F11: 328 | G11: Historia | H11: 7 | K11: 1722
A12: El lector de Julio Verne | B12: Almudena Grandes | C12: Propio | D12: 43929 | E12: 44113 | F12: 417 | G12: Novela | H12: 7.5 | K12: 2020
A13: Miles Vorkosigan XIII – Una campaña civil | B13: Lois McMaster Bujold | C13: ebook | D13: 43936 | E13: 43968 | F13: 496 | G13: Novela | H13: 8 | K13: 1999
A14: Las legendarias aventuras de Chiquito | B14: Sergio Mora | C14: Propio | D14: 43830 | E14: 43958 | F14: 192 | G14: Historieta | H14: 10 | K14: 2019
... A16: Casa de soles | B16: Alastair Reynolds | C16: ebook | D16: 43970 | E16: 43996 | F16: 384 | G16: Cuento | H16: 7 | K16: 2004
A17: Historia verdadera de la conquista de la Nueva España | B17: Bernal Diaz del Castillo | C17: ebook | D17: 43976 | F17: 1051 | G17: Historia | K17: 1632
A18: La Italia del año mil | B18: Indro Montanelli | C18: Prestado | D18: 43987 | E18: 43995 | F18: 302 | G18: Historia | H18: 8 | K18: 1966
A19: Cuentos de Canterbury | B19: Geoffrey Chaucer | C19: ebook | D19: 43996 | E19: 44070 | F19: 646 | G19: Cuentos | H19: 7 | K19: 1392
A20: Flores para Algernon | B20: Daniel Keyes | C20: ebook | D20: 44009 | E20: 44016 | F20: 311 | G20: Novela | H20: 8 | K20: 1959
A21: Cortés | B21: Christian Duverger | C21: ebook | D21: 44016 | E21: 44017 | F21: 480 | G21: Historia | H21: 7 | K21: 2013
A22: Asinaria - Aulularia - Miles Gloriosus | B22: Tito Maccio Plauto | C22: ebook | D22: 44017 | E22: 44020 | F22: 153 | G22: Teatro | H22: 7 | K22: -206
A23: Super Freakonomics | B23: Stephen Levitt y Stephen Dubner | C23: ebook | D23: 44022 | E23: 44024 | F23: 320 | G23: Divulgación | H23: 9 | K23: 2010
A24: Mundo azul | B24: Jack Vance | C24: ebook | D24: 44024 | E24: 44026 | F24: 272 | G24: Novela | H24: 7 | K24: 1966
A25: Balas de plata | B25: Elmer Mendoza | C25: ebook | D25: 44026 | E25: 44034 | F25: 254 | G25: Novela | H25: 8 | K25: 2008
A26: La prueba del ácido | B26: Elmer Mendoza | C26: ebook | D26: 44034 | E26: 44037 | F26: 400 | G26: Novela | H26: 8 | K26: 2010
A27: Nombres de perro | B27: Elmer Mendoza | C27: ebook | D27: 44037 | E27: 44040 | F27: 216 | G27: Novela | H27: 8 | K27: 2012
A28: Besar al detective | B28: Elmer Mendoza | C28: ebook | D28: 44040 | E28: 44042 | F28: 256 | G28: Novela | H28: 6.8 | K28: 2015
A29: A través de Marte | B29: Geoffrey A. Landis | C29: ebook | D29: 44042 | E29: 44049 | F29: 320 | G29: Novela | H29: 6 | K29: 2000
... A31: Ur, Asur y Babilonia | B31: Hartmut Schmökel | C31: ebook | D31: 44049 | E31: 44054 | F31: 294 | G31: Historia | H31: 7.5 | K31: 1965
A32: Los nueve libros de la historia | B32: Herodoto de Halicarnaso | C32: ebook | D32: 44054 | F32: 1383 | G32: Historia | K32: -430
A33: Cicatriz | B33: Juan Gomez Jurado | C33: ebook | D33: 44060 | E33: 44064 | F33: 576 | G33: Novela | H33: 7 | K33: 2015
A34: Había una vez...Sr Chinarro (conversaciones con Antonio Luque) | B34: Manuel Pinazo y Chema Domínguez | C34: Propio | D34: 44067 | E34: 44072 | F34: 240 | G34: Música | H34: 8.5 | K34: 2019
A35: La colmena | B35: Camilo José Cela | C35: ebook | D35: 44070 | E35: 44073 | F35: 336 | G35: Novela | H35: 6.5 | K35: 1950
A36: Bodas de sangre | B36: Federico García Lorca | C36: ebook | D36: 44073 | E36: 44074 | F36: 176 | G36: Teatro | H36: 8 | K36: 1933
A37: Cuando falla la gravedad (Trilogía 1) | B37: George Alec Effinger | C37: ebook | D37: 44074 | E37: 44087 | F37: 226 | G37: Novela | H37: 8.5 | K37: 1987
A38: 50 cosas que hay que saber sobre el universo | B38: Joanne Baker | C38: ebook | D38: 44087 | E38: 44101 | F38: 224 | G38: Divulgación | H38: 7.5 | K38: 2010
A39: La formación de América del Norte | B39: Isaac Asimov | C39: Propio | D39: 44094 | E39: 44127 | F39: 344 | G39: Historia | H39: 8.5 | K39: 1973
A40: Los Modlin | B40: Paco Gomez | C40: Prestado | D40: 44113 | E40: 44116 | F40: 288 | G40: Ensayo | H40: 8 | K40: 2019
A41: El hombre del traje negro | B41: Stephen King | C41: Propio | D41: 44117 | E41: 44121 | F41: 128 | G41: Cuento | H41: 8 | K41: 2017
A42: El universo en tu mano | B42: Christophe Galfard | C42: Propio | D42: 44127 | E42: 44151 | F42: 464 | G42: Divulgación | H42: 0 | K42: 2015
A43: El cine según Hitchcock | B43: François Truffaut | C43: Prestado | D43: 44150 | E43: 44173 | F43: 383 | G43: Cine | H43: 9 | K43: 1967
A44: Un fuego en el sol (Trilogía 2) | B44: George Alec Effinger | C44: ebook | D44: 44185 | E44: 44194 | F44: 320 | G44: Novela | H44: 9 | K44: 1989
F45: =SUMIFS(F2:F44,E2:E44,">0") -> 14579 | H45: =GEOMEAN(H2:H44) -> 0 | I45: =NA() -> #N/A | J45: =NA() -> #N/A
A46: Estadísticas | I46: =NA() -> #N/A | J46: =NA() -> #N/A
A47: Libros Leídos | B47: Media páginas por libro | C47: Autor más leido | D47: Tipo más leido | I47: =NA() -> #N/A | J47: =NA() -> #N/A
A48: =COUNTIF(E2:E44,">0") -> 40 | B48: =ROUND(F45/A48,0) -> 364 | C48: =INDEX(J4:J69,MATCH(MAX(I4:I69),I4:I69,0),1) -> #N/A | I48: =NA() -> #N/A | J48: =NA() -> #N/A
I49: =NA() -> #N/A | J49: =NA() -> #N/A
I50: =NA() -> #N/A | J50: =NA() -> #N/A
I51: =NA() -> #N/A | J51: =NA() -> #N/A
I52: =NA() -> #N/A | J52: =NA() -> #N/A
I53: =NA() -> #N/A | J53: =NA() -> #N/A
I54: =NA() -> #N/A | J54: =NA() -> #N/A
I55: =NA() -> #N/A | J55: =NA() -> #N/A
I56: =NA() -> #N/A | J56: =NA() -> #N/A
I57: =NA() -> #N/A | J57: =NA() -> #N/A
I58: =NA() -> #N/A | J58: =NA() -> #N/A
I59: =NA() -> #N/A | J59: =NA() -> #N/A
I60: =NA() -> #N/A | J60: =NA() -> #N/A
... I69: =NA() -> #N/A | J69: =NA() -> #N/A

Sheet Leídos 2021
A1: Titulo | B1: Autor | C1: Origen | D1: Fecha Inicio | E1: Fecha Fin | F1: Paginas | G1: Tipo | H1: Puntuación (del 1 al 10) | I1: Num leidos | J1: Autor | K1: Año
A2: (Ekumen 4) La mano izquierda de la oscuridad | B2: Ursula K. Le Guin | C2: ebook | D2: 43318 | F2: 304 | G2: Novela | K2: 1969
A3: Historia verdadera de la conquista de la Nueva España | B3: Bernal Diaz del Castillo | C3: ebook | D3: 43976 | F3: 1051 | G3: Historia | K3: 1632
A4: Los nueve libros de la historia | B4: Herodoto de Halicarnaso | C4: ebook | D4: 44054 | F4: 1383 | G4: Historia | K4: -430
A5: El beso del exilio (Trilogía 3) | B5: George Alec Effinger | C5: ebook | D5: 44194 | E5: 44197 | F5: 272 | G5: Novela | H5: 7 | K5: 1991
A6: Miles Vorkosigan 14 – Inmunidad diplomática | B6: Lois McMaster Bujold | C6: ebook | D6: 44197 | E6: 44202 | F6: 320 | G6: Novela | H6: 7.5 | K6: 2002
A7: Miles Vorkosigan 15 – Criopolis | B7: Lois McMaster Bujold | C7: ebook | D7: 44203 | E7: 44247 | F7: 381 | G7: Novela | H7: 8 | K7: 2010
A8: Viaje de Londres a Génova a través de Inglaterra, Portugal, España y Francia | B8: Giuseppe Baretti | C8: Propio | D8: 44203 | E8: 44227 | F8: 592 | G8: Ensayo | H8: 9 | K8: 1770
A9: Lemmy | B9: Ian Kilmister | C9: Propio | D9: 44219 | E9: 44254 | F9: 368 | G9: Biografía | H9: 8 | K9: 2016
A10: Stoner | B10: John Williams | C10: Propio | D10: 44227 | E10: 44256 | F10: 276 | G10: Novela | H10: 7 | K10: 1965
A11: Un abismo en el cielo | B11: Vernor Vinge | C11: ebook | D11: 44247 | E11: 44282 | F11: 400 | G11: Novela | H11: 8 | K11: 1999
A12: Un fuego sobre el abismo | B12: Vernor Vinge | C12: ebook | D12: 44282 | E12: 44406 | F12: 392 | G12: Novela | H12: 7 | K12: 1992
A13: Nieve en los bolsillos | B13: Kim | C13: Propio | D13: 44289 | E13: 44294 | F13: 191 | G13: Comic | H13: 9 | K13: 2018
A14: Las quince primeras vidas de Harry August | B14: Claire North | C14: Propio | D14: 44294 | E14: 44303 | F14: 416 | G14: Novela | H14: 8 | K14: 2014
A15: Mi ovni de la perestroika | B15: Daniel Utrilla | C15: Propio | D15: 44303 | E15: 44364 | F15: 648 | G15: Ensayo | H15: 7.5 | K15: 2021
A16: Un verdor terrible | B16: Benjamin Labatut | C16: Propio | D16: 44364 | E16: 44373 | F16: 212 | G16: Ensayo | H16: 9 | K16: 2015
... A18: Odorama: historia cultural del olor | B18: Federico Kukso | C18: Propio | D18: 44380 | E18: 44422 | F18: 432 | G18: Ensayo | H18: 7 | K18: 2019
A19: La guerra de la paz | B19: Vernor Vinge | C19: ebook | D19: 44406 | F19: 384 | G19: Novela | K19: 1984
A20: Brujas de Viaje | B20: Terry Pratchett | C20: ebook | D20: 44411 | E20: 44436 | F20: 320 | G20: Novela | H20: 7 | K20: 1991
A21: 1177 aC, el año en que la covilización se derrumbó | B21: Eric H. Cline | C21: Propio | D21: 44422 | E21: 44434 | F21: 360 | G21: Ensayo | K21: 2016
A22: El asesinato de García Lorca | B22: Ian Gibson | C22: Propio | D22: 44434 | E22: 44440 | F22: 608 | G22: Ensayo | H22: 8.5 | K22: 1979
A23: Pavana | B23: Keith Roberts | C23: ebook | D23: 44437 | E23: 44488 | F23: 288 | G23: Novela | H23: 6 | K23: 1968
A24: Poeta en Nueva York | B24: Federico García Lorca | C24: Propio | D24: 44440 | E24: 44460 | F24: 264 | G24: Poesía | H24: 9 | K24: 1940
A25: Niños Mutantes: 20 años, 20 canciones | B25: Julio Jiménez y Alfonso Mendez | C25: Propio | D25: 44460 | E25: 44461 | F25: 126 | G25: Ensayo | H25: 4 | K25: 2016
A26: Viaje al centro de mi cerebro | B26: Eric Jiménez | C26: Propio | D26: 44461 | E26: 44471 | F26: 220 | G26: Ensayo | H26: 5 | K26: 2021
A27: Americo Vespucio | B27: Stefan Zweig | C27: Propio | D27: 44472 | E27: 44475 | F27: 144 | G27: Ensayo | H27: 9 | K27: 1931
A28: Una guía de lectura “Llanto por Ignacio Sánchez Mejías” de Federico García Lorca | B28: Miguel Metzeltin y Martina Meidl | C28: Propio | D28: 44475 | E28: 44523 | F28: 173 | G28: Poesía | H28: 8 | K28: 1998
A29: Hermanos | B29: George Alec Effinger | C29: ebook | D29: 44489 | E29: 44554 | F29: 212 | G29: Novela | H29: 5 | K29: 1973
A30: Noventa por ciento de todo | B30: Rose George | C30: Propio | D30: 44523 | E30: 44553 | F30: 304 | G30: Ensayo | H30: 8 | K30: 2013
F31: =SUMIFS(F2:F29,E2:E29,">0") -> 7908 | H31: =GEOMEAN(H2:H29) -> 7.3496167 | I31: =NA() -> #N/A | J31: =NA() -> #N/A
A32: Estadísticas | I32: =NA() -> #N/A | J32: =NA() -> #N/A
A33: Libros Leídos | B33: Media páginas por libro | C33: Autor más leido | D33: Tipo más leido | I33: =NA() -> #N/A | J33: =NA() -> #N/A
A34: =COUNTIF(E2:E29,">0") -> 24 | B34: =ROUND(F31/A34,0) -> 330 | C34: =INDEX(J3:J55,MATCH(MAX(I3:I55),I3:I55,0),1) -> #N/A | I34: =NA() -> #N/A | J34: =NA() -> #N/A
I35: =NA() -> #N/A | J35: =NA() -> #N/A
I36: =NA() -> #N/A | J36: =NA() -> #N/A
I37: =NA() -> #N/A | J37: =NA() -> #N/A
I38: =NA() -> #N/A | J38: =NA() -> #N/A
I39: =NA() -> #N/A | J39: =NA() -> #N/A
I40: =NA() -> #N/A | J40: =NA() -> #N/A
I41: =NA() -> #N/A | J41: =NA() -> #N/A
I42: =NA() -> #N/A | J42: =NA() -> #N/A
I43: =NA() -> #N/A | J43: =NA() -> #N/A
I44: =NA() -> #N/A | J44: =NA() -> #N/A
I45: =NA() -> #N/A | J45: =NA() -> #N/A
I46: =NA() -> #N/A | J46: =NA() -> #N/A
... I55: =NA() -> #N/A | J55: =NA() -> #N/A

Sheet Leídos 2022
A1: Titulo | B1: Autor | C1: Origen | D1: Fecha Inicio | E1: Fecha Fin | F1: Paginas | G1: Tipo | H1: Puntuación (del 1 al 10) | I1: Num leidos | J1: Autor | K1: Año
A2: (Ekumen 4) La mano izquierda de la oscuridad | B2: Ursula K. Le Guin | C2: ebook | D2: 43318 | F2: 304 | G2: Novela | K2: 1969
A3: Historia verdadera de la conquista de la Nueva España | B3: Bernal Diaz del Castillo | C3: ebook | D3: 43976 | F3: 1051 | G3: Historia | K3: 1632
A4: Los nueve libros de la historia | B4: Herodoto de Halicarnaso | C4: ebook | D4: 44054 | F4: 1383 | G4: Historia | K4: -430
A5: La guerra de la paz | B5: Vernor Vinge | C5: ebook | D5: 44406 | F5: 384 | G5: Novela | K5: 1984
A6: El corazón del invierno | B6: Robert Jordan | C6: ebook | D6: 44554 | E6: 44651 | F6: 296 | G6: Novela | H6: 5 | K6: 2000
A7: Limonov | B7: Emmanuel Carrère | C7: Propio | D7: 44572 | E7: 44587 | F7: 400 | G7: Ensayo | H7: 9 | K7: 2012
A8: Proyecto Hail Mary | B8: Andy Weir | C8: Propio | D8: 44587 | E8: 44602 | F8: 544 | G8: Novela | H8: 8 | K8: 2021
A9: Berlanga, el último austrohúngaro | B9: Manuel Hidalgo | C9: Propio | D9: 44602 | E9: 44605 | F9: 289 | G9: Ensayo | H9: 9 | K9: 1981
A10: Warburg & Bleach | B10: Jorge Carrión | C10: Propio | D10: 44605 | E10: 44610 | F10: 76 | G10: Comic | H10: 6 | K10: 2021
A11: Bajo la sombra del Vesubio | B11: Daisy Dunn | C11: Propio | D11: 44610 | E11: 44624 | F11: 344 | G11: Ensayo | H11: 9 | K11: 2019
A12: Come as you are: Nirvana | B12: Michael Azerrad | C12: Propio | D12: 44624 | E12: 44648 | F12: 480 | G12: Música | H12: 9 | K12: 1993
A13: Walden | B13: Henry David Thoreau | C13: Propio | D13: 44649 | F13: 392 | G13: Ensayo | K13: 1854
A14: El viaje a ninguna parte | B14: Fernando Fernán Gómez | C14: ebook | D14: 44651 | E14: 44653 | F14: 320 | G14: Novela | H14: 9 | K14: 1985
A15: Iréne | B15: Pierre Lemaitre | C15: ebook | D15: 44653 | E15: 44656 | F15: 400 | G15: Novela | H15: 9 | K15: 2006
A16: Alex | B16: Pierre Lemaitre | C16: ebook | D16: 44656 | E16: 44666 | F16: 392 | G16: Novela | H16: 8 | K16: 2011
A17: Rosi & John | B17: Pierre Lemaitre | C17: ebook | D17: 44666 | E17: 44694 | F17: 392 | G17: Novela | H17: 8 | K17: 2016
A18: Peste & Cólera | B18: Patrick Deville | C18: ebook | D18: 44694 | E18: 44710 | F18: 240 | G18: Ensayo | H18: 7 | K18: 2012
A19: Guía del Antiguo Testamento | B19: Isaac Asimov | C19: ebook | D19: 44696 | E19: 44707 | F19: 656 | G19: Historia | H19: 8 | K19: 1968
A20: Historia de los godos | B20: Rosa Sanz Serrano | C20: ebook | D20: 44710 | E20: 44735 | F20: 582 | G20: Historia | H20: 6 | K20: 2009
A21: Historia Natural – Libros I-II | B21: Plinio el Viejo | C21: ebook | D21: 44735 | F21: 446 | G21: Historia | K21: 70
A22: El sindicato de policía yidish | B22: Michael Chabon | C22: ebook | D22: 44740 | E22: 44751 | F22: 432 | G22: Novela | H22: 7 | K22: 2007
A23: Al-Andalus | B23: Angel Vera Aranda | C23: ebook | D23: 44751 | E23: 44756 | F23: 349 | G23: Historia | K23: 2014
A24: Tres piedras hacen una pared | B24: Eric H. Cline | C24: ebook | D24: 44756 | E24: 44763 | F24: 576 | G24: Ensayo | H24: 8 | K24: 2007
A25: El apagón | B25: Connie Willis | C25: ebook | D25: 44763 | E25: 44771 | F25: 624 | G25: Novela | H25: 8 | K25: 2011
A26: Hijos de Febrero | B26: Alan Parks | C26: ebook | D26: 44771 | E26: 44773 | F26: 438 | G26: Novela | H26: 8 | K26: 2021
A27: El color de la magia | B27: Terry Pratchett | C27: ebook | D27: 44773 | E27: 44776 | F27: 288 | G27: Novela | H27: 7 | K27: 1983
A28: La Alta Edad media | B28: Isaac Asimov | C28: ebook | D28: 44776 | E28: 44782 | F28: 272 | G28: Historia | H28: 7 | K28: 1970
A29: La formación de Inglatera | B29: Isaac Asimov | C29: ebook | D29: 44782 | E29: 44785 | F29: 360 | G29: Historia | H29: 7 | K29: 1969
A30: La tierra de Canaan | B30: Isaac Asimov | C30: ebook | D30: 44785 | E30: 44789 | F30: 400 | G30: Historia | H30: 6.5 | K30: 1971
A31: La larga marcha | B31: Rafael Chirbes | C31: ebook | D31: 44789 | E31: 44800 | F31: 392 | G31: Novela | H31: 8 | K31: 1996
A32: Progenie | B32: Susana Martin Gijón | C32: Propio | D32: 44791 | E32: 44794 | F32: 432 | G32: Novela | H32: 7 | K32: 2020
A33: Civilizaciones | B33: Laurence Binet | C33: Propio | D33: 44794 | E33: 44797 | F33: 448 | G33: Novela | H33: 9 | K33: 2020
A34: Mendigos de España | B34: Nancy Kerr | C34: ebook | D34: 44800 | E34: 44807 | F34: 576 | G34: Novela | H34: 8 | K34: 1991
A35: Rechicero | B35: Terry Pratchett | C35: ebook | D35: 44807 | E35: 44818 | F35: 320 | G35: Novela | H35: 8 | K35: 1988
... A39: The peripheral | B39: William Gibson | C39: ebook | D39: 44836 | E39: 44874 | F39: 528 | G39: Novela | H39: 8 | K39: 2014
A40: Otros mundos | B40: Thomas Halliday | C40: Propio | D40: 44860 | F40: 416 | G40: Ensayo | K40: 2022
A41: Mundo Anillo | B41: Larry Niven | C41: ebook | D41: 44874 | E41: 44893 | F41: 320 | G41: Novela | H41: 8 | K41: 1970
A42: The Power | B42: Naomi Alderman | C42: ebook | D42: 44893 | E42: 44906 | F42: 352 | G42: Novela | H42: 8.5 | K42: 2016
A43: Cronopaisaje | B43: Gregory Benford | C43: ebook | D43: 44907 | E43: 44925 | F43: 352 | G43: Novela | H43: 8.7 | K43: 1980
F44: =SUMIFS(F2:F43,E2:E43,">0") -> 13862 | H44: =GEOMEAN(H2:H43) -> 7.7451006 | I44: =NA() -> #N/A | J44: =NA() -> #N/A
A45: Estadísticas | I45: =NA() -> #N/A | J45: =NA() -> #N/A
A46: Libros Leídos | B46: Media páginas por libro | C46: Autor más leido | D46: Tipo más leido | I46: =NA() -> #N/A | J46: =NA() -> #N/A
A47: =COUNTIF(E2:E43,">0") -> 35 | B47: =ROUND(F44/A47,0) -> 396 | C47: =INDEX(J3:J68,MATCH(MAX(I3:I68),I3:I68,0),1) -> #N/A | I47: =NA() -> #N/A | J47: =NA() -> #N/A
I48: =NA() -> #N/A | J48: =NA() -> #N/A
I49: =NA() -> #N/A | J49: =NA() -> #N/A
I50: =NA() -> #N/A | J50: =NA() -> #N/A
I51: =NA() -> #N/A | J51: =NA() -> #N/A
I52: =NA() -> #N/A | J52: =NA() -> #N/A
I53: =NA() -> #N/A | J53: =NA() -> #N/A
I54: =NA() -> #N/A | J54: =NA() -> #N/A
I55: =NA() -> #N/A | J55: =NA() -> #N/A
I56: =NA() -> #N/A | J56: =NA() -> #N/A
I57: =NA() -> #N/A | J57: =NA() -> #N/A
I58: =NA() -> #N/A | J58: =NA() -> #N/A
I59: =NA() -> #N/A | J59: =NA() -> #N/A
... I68: =NA() -> #N/A | J68: =NA() -> #N/A

Sheet Leídos 2023
A1: Titulo | B1: Autor | C1: Origen | D1: Fecha Inicio | E1: Fecha Fin | F1: Paginas | G1: Tipo | H1: Puntuación (del 1 al 10) | I1: Num leidos | J1: Autor | K1: Año
A2: El artefacto | B2: Gregory Benford | C2: ebook | D2: 44925 | E2: 44934 | F2: 400 | G2: Novela | H2: 7 | K2: 1980
A3: El fin de la infancia | B3: Arthur C. Clarke | C3: ebook | D3: 44934 | E3: 44952 | F3: 232 | G3: Novela | H3: 7 | K3: 1953
A4: Los reyes de la Alhambra: entre la historia y la leyenda | B4: Francisco Bueno García | C4: Propio | D4: 44938 | E4: 44983 | F4: 757 | G4: Historia | H4: 7 | K4: 2003
A5: Picnic extraterrestre | B5: Arkadi Strugatski y Boris Natanovich Strugatskiï | C5: ebook | D5: 44952 | E5: 44967 | F5: 192 | G5: Novela | H5: 8 | K5: 1972
A6: La paja en el Ojo de Dios | B6: Larry Niven y Jerry Pournelle | C6: ebook | D6: 44967 | E6: 45004 | F6: 512 | G6: Novela | H6: 8 | K6: 1974
A7: La risa en la antigua Roma | B7: Mary Beard | C7: Propio | D7: 44984 | E7: 45060 | F7: 380 | G7: Historia | H7: 6 | K7: 2022
A8: En la estación Basilisco | B8: David Weber | C8: ebook | D8: 45004 | E8: 45023 | F8: 310 | G8: Novela | H8: 7 | K8: 1993
A9: Justicia auxiliar | B9: Ann Leckie | C9: ebook | D9: 45024 | E9: 45043 | F9: 416 | G9: Novela | H9: 5 | K9: 2013
A10: Henders | B10: Warren Fahy | C10: ebook | D10: 45043 | E10: 45049 | F10: 400 | G10: Novela | H10: 6.8 | K10: 2010
A11: Cómo descubrimos los números | B11: Isaac Asimov | C11: ebook | D11: 45049 | E11: 45050 | F11: 20 | G11: Historia | H11: 7 | K11: 1981
A12: El honor de la reina | B12: David Weber | C12: ebook | D12: 45050 | E12: 45067 | F12: 352 | G12: Novela | H12: 7 | K12: 1993
A13: Las calles siniestras | B13: Pio Baroja | C13: Propio | D13: 45060 | E13: 45172 | F13: 268 | G13: Relatos | H13: 6 | K13: 2019
... A48: La estrella de Pandora | B48: Peter Hamilton | C48: ebook | D48: 45266 | E48: 45290 | F48: 762 | G48: Novela | H48: 8 | K48: 2008
F49: =SUMIFS(F2:F48,E2:E48,">0") -> 17489 | H49: =GEOMEAN(H2:H48) -> 6.9350861 | I49: =NA() -> #N/A | J49: =NA() -> #N/A
A50: Estadísticas | I50: =NA() -> #N/A | J50: =NA() -> #N/A
A51: Libros Leídos | B51: Media páginas por libro | C51: Autor más leido | D51: Tipo más leido | I51: =NA() -> #N/A | J51: =NA() -> #N/A
A52: =COUNTIF(E2:E48,">0") -> 47 | B52: =ROUND(F49/A52,0) -> 372 | C52: =INDEX(J2:J73,MATCH(MAX(I2:I73),I2:I73,0),1) -> #N/A | I52: =NA() -> #N/A | J52: =NA() -> #N/A
I53: =NA() -> #N/A | J53: =NA() -> #N/A
I54: =NA() -> #N/A | J54: =NA() -> #N/A
I55: =NA() -> #N/A | J55: =NA() -> #N/A
I56: =NA() -> #N/A | J56: =NA() -> #N/A
I57: =NA() -> #N/A | J57: =NA() -> #N/A
I58: =NA() -> #N/A | J58: =NA() -> #N/A
I59: =NA() -> #N/A | J59: =NA() -> #N/A
I60: =NA() -> #N/A | J60: =NA() -> #N/A
I61: =NA() -> #N/A | J61: =NA() -> #N/A
I62: =NA() -> #N/A | J62: =NA() -> #N/A
I63: =NA() -> #N/A | J63: =NA() -> #N/A
I64: =NA() -> #N/A | J64: =NA() -> #N/A
... I73: =NA() -> #N/A | J73: =NA() -> #N/A

Sheet Leídos 2024
A1: Titulo | B1: Autor | C1: Origen | D1: Fecha Inicio | E1: Fecha Fin | F1: Paginas | G1: Tipo | H1: Puntuación (del 1 al 10) | I1: Num leidos | J1: Autor | K1: Año
A2: (Ekumen 4) La mano izquierda de la oscuridad | B2: Ursula K. Le Guin | C2: ebook | D2: 43318 | F2: 304 | G2: Novela | K2: 1969
A3: Otros mundos | B3: Thomas Halliday | C3: Propio | D3: 44860 | F3: 416 | G3: Ensayo | K3: 2022
A4: La divina comedia | B4: Dante Alighlieri | C4: Propio | D4: 44929 | F4: 668 | G4: Poema | K4: 1320
A5: La guerra de la paz | B5: Vernor Vinge | C5: ebook | D5: 44406 | F5: 384 | G5: Novela | K5: 1984
A6: Accelerando | B6: Charles Stross | C6: Propio | D6: 45124 | F6: 351 | G6: Novela | K6: 2005
A7: Cuentos completos 1 | B7: Philip K. Dick | C7: Propio | F7: 651 | G7: Relatos | K7: 1987
A8: El origen de las especies | B8: Charles Darwin | C8: Propio | F8: 676 | G8: Ensayo | K8: 2019
A9: Abrázame hasta que esta vida deje de dar puto asco | B9: Juarma | C9: Propio | F9: 150 | G9: Comic | K9: 2022
A10: Rayuela | B10: Julio Cortazar | C10: Propio | F10: 746 | G10: Novela | K10: 1984
A11: Meditaciones | B11: Ignatius Farray | C11: Propio | F11: 218 | G11: Ensayo | K11: 2022
A12: Historia de la literatura romana | B12: Ludwig Bieler | C12: Propio | D12: 45231 | F12: 336 | G12: Historia | K12: 1972
A13: Artemis | B13: Andy Weir | C13: Propio | D13: 45275 | E13: 45359 | F13: 368 | G13: Novela | H13: 7 | K13: 2017
A14: Todo está perdonado | B14: Rafael Reig | C14: Propio | D14: 45204 | E14: 45316 | F14: 367 | G14: Novela | H14: 6 | K14: 2011
A15: Judas desencadenado | B15: Peter F. Hamilton | C15: ebook | D15: 45290 | E15: 45306 | F15: 868 | G15: Novela | H15: 7 | K15: 2005
A16: Toda la historia del mundo: de la prehistoria a la actualidad | B16: Jean-Claude Barreau | C16: ebook | D16: 45296 | E16: 45314 | F16: 480 | G16: Historia | H16: 6 | K16: 2006
A17: La colonia perdida | B17: John Scalzi | C17: ebook | D17: 45306 | E17: 45311 | F17: 304 | G17: Novela | H17: 6.9 | K17: 2007
A18: El fuego elemental | B18: Martha Wells | C18: ebook | D18: 45315 | E18: 45327 | F18: 443 | G18: Novela | H18: 7 | K18: 2006
A19: Exhalación | B19: Ted Chiang | C19: Propio | D19: 45316 | E19: 45324 | F19: 343 | G19: Relatos | H19: 8 | K19: 2019
A20: La Granada ignorada | B20: Juan Carlos Perez Sanchez | C20: Propio | D20: 45324 | E20: 45333 | F20: 186 | G20: Historia | H20: 8 | K20: 2023
A21: Sistemas críticos (Los diarios de Matabot 1) | B21: Martha Wells | C21: ebook | D21: 45329 | E21: 45332 | F21: 152 | G21: Novela | H21: 7.7 | K21: 2019
A22: Japan Sinks | B22: Sakyo Komatsu | C22: Propio | D22: 45328 | F22: 494 | G22: Novela | K22: 1973
A23: Condición artificial (Los diarios de Matabot 2) | B23: Martha Wells | C23: ebook | D23: 45333 | E23: 45336 | F23: 160 | G23: Novela | H23: 7.5 | K23: 2019
A24: Britania conquistada | B24: Harry Turtledove | C24: ebook | D24: 45336 | E24: 45347 | F24: 651 | G24: Novela | H24: 7 | K24: 2002
A25: Pensad en Feblas | B25: Iain Banks | C25: ebook | D25: 45347 | E25: 45369 | F25: 649 | G25: Novela | H25: 7 | K25: 1987
A26: Sid Meier's Memoir!: A Life in Computer Games | B26: Sid Meier | C26: Propio | D26: 45359 | E26: 45452 | F26: 304 | G26: Memorias | H26: 7 | K26: 2020
A27: Bailén | B27: Benito Pérez Galdós | C27: ebook | D27: 45369 | E27: 45373 | F27: 160 | G27: Novela | H27: 7 | K27: 1873
A28: El orgullo de Chanur (La saga de Chanur 1) | B28: C.J. Cherryh | C28: ebook | D28: 45373 | E28: 45380 | F28: 331 | G28: Novela | K28: 1984
A29: Historia de Zoe (La vieja guardia 4) | B29: John Scalzi | C29: ebook | D29: 45380 | E29: 45382 | F29: 352 | G29: Novela | H29: 6.5 | K29: 2010
A30: Intrépido (La flota perdida 1) | B30: Jack Campbell | C30: ebook | D30: 45382 | E30: 45394 | F30: 422 | G30: Novela | H30: 7 | K30: 2006
A31: La familia de Pascual Duarte | B31: Camilo José Cela | C31: ebook | D31: 45394 | E31: 45398 | F31: 118 | G31: Novela | H31: 7 | K31: 1942
A32: El sueño del androide | B32: John Scalzi | C32: ebook | D32: 45398 | E32: 45401 | F32: 412 | G32: Novela | H32: 7 | K32: 2006
A33: El jugador | B33: Iain Banks | C33: ebook | D33: 45401 | E33: 45422 | F33: 386 | G33: Novela | H33: 7.5 | K33: 1988
A34: Deus ex | B34: Ferdia Lennon | C34: Propio | D34: 45413 | E34: 45419 | F34: 288 | G34: Novela | H34: 8.4 | K34: 2023
A35: Eon | B35: Greg Bear | C35: ebook | D35: 45422 | E35: 45439 | F35: 763 | G35: Novela | H35: 5 | K35: 1985
A36: El viaje de la humanidad | B36: Oded Galor | C36: Propio | D36: 45422 | E36: 45427 | F36: 373 | G36: Ensayo | H36: 6.5 | K36: 2022
A37: Radicalizado | B37: Cory Doctorow | C37: Propio | D37: 45427 | E37: 45430 | F37: 261 | G37: Ensayo | H37: 7 | K37: 2019
A38: Muerte en abril | B38: Alan Parks | C38: Propio | D38: 45436 | E38: 45438 | F38: 416 | G38: Novela | H38: 7 | K38: 2023
A39: Napoleón en Chamartin | B39: Benito Pérez Galdós | C39: ebook | D39: 45440 | E39: 45446 | F39: 352 | G39: Novela | H39: 6.5 | K39: 1874
A40: La busca | B40: Pio Baroja | C40: ebook | D40: 45446 | E40: 45452 | F40: 352 | G40: Novela | H40: 8 | K40: 1902
... A44: Redshirts | B44: John Scalzi | C44: ebook | D44: 45473 | E44: 45476 | F44: 320 | G44: Novela | H44: 8 | K44: 2012
A45: Cese de alerta | B45: Connie Willis | C45: Propio | D45: 45460 | E45: 45535 | F45: 732 | G45: Novela | K45: 2013
A46: El vacío de los sueños | B46: Peter F. Hamilton | C46: ebook | D46: 45476 | E46: 45486 | F46: 837 | G46: Novela | H46: 7 | K46: 2011
A47: Historia de dos ciudades | B47: Charles Dickens | C47: ebook | D47: 45486 | E47: 45491 | F47: 275 | G47: Novela | H47: 5 | K47: 1859
A48: Los egipcios | B48: Isaac Asimov | C48: ebook | D48: 45491 | E48: 45496 | F48: 336 | G48: Historia | H48: 7 | K48: 1967
A49: Se desataron todos los infiernos | B49: Max Hastings | C49: ebook | D49: 45496 | E49: 45509 | F49: 1214 | G49: Historia | H49: 8 | K49: 2011
A50: Atenas clásica | B50: Peter Funke | C50: ebook | D50: 45509 | E50: 45516 | F50: 144 | G50: Historia | H50: 7 | K50: 2001
A51: Okinawa: la última batalla | B51: Bill Sloan | C51: ebook | D51: 45516 | E51: 45523 | F51: 480 | G51: Historia | H51: 8 | K51: 2008
A52: El arbol de la ciencia | B52: Pio Baroja | C52: ebook | D52: 45523 | E52: 45528 | F52: 304 | G52: Novela | H52: 6.7 | K52: 1911
A53: El puente | B53: Iain Banks | C53: ebook | D53: 45528 | E53: 45533 | F53: 297 | G53: Novela | H53: 7.8 | K53: 1986
A54: ¿Está usted de broma, señor Feynman? | B54: Richard Feynman | C54: ebook | D54: 45533 | E54: 45539 | F54: 497 | G54: Memorias | H54: 5 | K54: 1985
A55: California 83 | B55: Pepe Colubi | C55: Propio | D55: 45535 | E55: 45547 | F55: 394 | G55: Novela | H55: 8 | K55: 2008
A56: El tercer brazo | B56: Larry Niven y Jerry Pournelle | C56: ebook | D56: 45539 | E56: 45555 | F56: 556 | G56: Novela | H56: 7.2 | K56: 1993
A57: El zoo de papel | B57: Ken Liu | C57: Propio | D57: 45547 | E57: 45587 | F57: 544 | G57: Novela | H57: 9 | K57: 2017
... A71: Sin memoria | B71: Brian Freeman | C71: ebook | D71: 45633 | E71: 45642 | F71: 480 | G71: Novela | H71: 6.8 | K71: 2015
F72: =SUMIFS(F2:F71,E2:E71,">0") -> 23457 | H72: =GEOMEAN(H2:H71) -> 6.9974829 | I72: =NA() -> #N/A | J72: =NA() -> #N/A
A73: Estadísticas | I73: =NA() -> #N/A | J73: =NA() -> #N/A
A74: Libros Leídos | B74: Media páginas por libro | C74: Autor más leido | D74: Tipo más leido | I74: =NA() -> #N/A | J74: =NA() -> #N/A
A75: =COUNTIF(E2:E71,">0") -> 58 | B75: =ROUND(F72/A75,0) -> 404 | C75: =INDEX(J3:J96,MATCH(MAX(I3:I96),I3:I96,0),1) -> #N/A | I75: =NA() -> #N/A | J75: =NA() -> #N/A
I76: =NA() -> #N/A | J76: =NA() -> #N/A
I77: =NA() -> #N/A | J77: =NA() -> #N/A
I78: =NA() -> #N/A | J78: =NA() -> #N/A
I79: =NA() -> #N/A | J79: =NA() -> #N/A
I80: =NA() -> #N/A | J80: =NA() -> #N/A
I81: =NA() -> #N/A | J81: =NA() -> #N/A
I82: =NA() -> #N/A | J82: =NA() -> #N/A
I83: =NA() -> #N/A | J83: =NA() -> #N/A
I84: =NA() -> #N/A | J84: =NA() -> #N/A
I85: =NA() -> #N/A | J85: =NA() -> #N/A
I86: =NA() -> #N/A | J86: =NA() -> #N/A
I87: =NA() -> #N/A | J87: =NA() -> #N/A
... I96: =NA() -> #N/A | J96: =NA() -> #N/A

Sheet Leídos 2025
A1: Titulo | B1: Autor | C1: Origen | D1: Fecha Inicio | E1: Fecha Fin | F1: Paginas | G1: Tipo | H1: Puntuación (del 1 al 10) | I1: Num leidos | J1: Autor | K1: Año
A2: Sostener el cielo | B2: Liu Cixin | C2: Propio | D2: 45631 | E2: 45698 | F2: 392 | G2: Relatos | H2: 8 | K2: 2024
A3: El vacío temporal | B3: Peter F. Hamilton | C3: ebook | D3: 45642 | E3: 45659 | F3: 544 | G3: Novela | H3: 7 | K3: 2012
A4: La Primera Guerra Mundial | B4: Martin Gilbert | C4: ebook | D4: 45659 | E4: 45677 | F4: 928 | G4: Historia | H4: 7 | K4: 1986
A5: Y fundaremos la ciudad más grande del mundo | B5: Giovanni Nucci | C5: Propio | D5: 45664 | E5: 45673 | F5: 162 | G5: Historia | H5: 8 | K5: 2020
A6: Pax | B6: Tom Holland | C6: Propio | D6: 45673 | E6: 45693 | F6: 480 | G6: Historia | H6: 7 | K6: 2024
A7: Cosmo | B7: Gregory Benford | C7: ebook | D7: 45677 | E7: 45694 | F7: 384 | G7: Novela | H7: 6.5 | K7: 1999
A8: Hombres fósiles | B8: Kermit Pattison | C8: Propio | D8: 45693 | E8: 45706 | F8: 544 | G8: Ensayo | H8: 8 | K8: 2024
A9: Pórtico | B9: Frederik Pohl | C9: ebook | D9: 45694 | E9: 45708 | F9: 368 | G9: Novela | H9: 8 | K9: 1977
A10: Nexus | B10: Yuval Noah Harari | C10: Propio | D10: 45707 | E10: 45731 | F10: 608 | G10: Ensayo | H10: 8 | K10: 2024
A11: A través del mar de soles | B11: Gregory Benford | C11: ebook | D11: 45708 | E11: 45722 | F11: 457 | G11: Novela | H11: 7 | K11: 1984
A12: El gran rio del espacio | B12: Gregory Benford | C12: ebook | D12: 45722 | E12: 45737 | F12: 471 | G12: Novela | H12: 6.5 | K12: 1987
A13: Las metamorfosis | B13: Publio Ovidio Nasón | C13: Propio | D13: 45726 | E13: 45998 | F13: 480 | G13: Poesia | H13: 5.5 | K13: 8
... A21: Muertes de perro | B21: Francisco Ayala | C21: ebook | D21: 45809 | E21: 45823 | F21: 301 | G21: Novela | H21: 7.5 | K21: 1958
A22: Cultivar un huerto para Dummies | B22: Grazia Cacciola | C22: ebook | D22: 45813 | E22: 45816 | G22: Ensayo | K22: 2022
A23: Madrid DF | B23: Fernando Caballero | C23: Propio | D23: 45818 | E23: 45826 | F23: 392 | G23: Ensayo | H23: 6 | K23: 2024
A24: Origenes | B24: Lewis Dartnell | C24: ebook | D24: 45823 | E24: 45836 | F24: 400 | G24: Historia | H24: 7.5 | K24: 2019
A25: El infinito en un junco | B25: Irene Vallejo | C25: Propio | D25: 45829 | E25: 45860 | F25: 452 | G25: Ensayo | H25: 9 | K25: 2019
A26: Diez días que estremecieron al mundo | B26: John Reed | C26: ebook | D26: 45836 | E26: 45845 | F26: 448 | G26: Historia | H26: 5 | K26: 1919
A27: Las joyas de la Castafiore | B27: Hergé | C27: Propio | D27: 45850 | E27: 45851 | F27: 80 | G27: Comic | H27: 7 | K27: 1962
A28: Ready player one | B28: Ernest Cline | C28: ebook | D28: 45845 | E28: 45859 | F28: 464 | G28: Novela | K28: 2011
A29: La ciudad y la ciudad | B29: China Mieville | C29: ebook | D29: 45859 | E29: 45867 | F29: 320 | G29: Novela | H29: 6 | K29: 2014
A30: El loto azul | B30: Hergé | C30: Propio | D30: 45861 | E30: 45862 | F30: 64 | G30: Comic | H30: 7 | K30: 1935
A31: Elogio del futuro | B31: Eudald Carbonell | C31: Propio | D31: 45860 | E31: 45872 | F31: 128 | G31: Ensayo | H31: 4.5 | K31: 2018
A32: Tintín en el Congo | B32: Hergé | C32: Propio | D32: 45863 | E32: 45863 | F32: 69 | G32: Comic | H32: 6 | K32: 1931
A33: Los cigarros del faraón | B33: Hergé | C33: Propio | D33: 45863 | E33: 45863 | F33: 62 | G33: Comic | H33: 6.5 | K33: 1934
A34: El cetro de Ottokar | B34: Hergé | C34: Propio | D34: 45864 | E34: 45864 | F34: 64 | G34: Comic | H34: 7.4 | K34: 1938
A35: El agente de las estrellas | B35: John Scalzi | C35: ebook | D35: 45867 | E35: 45871 | F35: 320 | G35: Novela | H35: 7 | K35: 2005
A36: Estación Amarinta I | B36: Jack Vance | C36: ebook | D36: 45871 | E36: 45884 | F36: 403 | G36: Novela | H36: 7.5 | K36: 1987
A37: Felipe II | B37: Geofrrey Parker | C37: Propio | D37: 45872 | E37: 45901 | F37: 1436 | G37: Historia | H37: 8.6 | K37: 2012
A38: Estación Amarinta II | B38: Jack Vance | C38: ebook | D38: 45884 | E38: 45892 | F38: 290 | G38: Novela | H38: 8 | K38: 1987
A39: Ecce y la Vieja Tierra | B39: Jack Vance | C39: ebook | D39: 45892 | E39: 45907 | F39: 352 | G39: Novela | H39: 7 | K39: 1989
A40: Spaceships Over Glasgow: Mogwai, Mayhem and Misspent Youth | B40: Stuart Braithwaite | C40: Propio | D40: 45901 | E40: 45951 | F40: 320 | G40: Memorias | H40: 6 | K40: 2022
A41: 2312 | B41: Kim Stanley Robinson | C41: ebook | D41: 45907 | E41: 45925 | F41: 528 | G41: Novela | H41: 4 | K41: 2012
A42: El capitán Alatriste | B42: Arturo Pérez-Reverte | C42: ebook | D42: 45913 | E42: 45914 | F42: 248 | G42: Novela | H42: 8 | K42: 1996
A43: Limpieza de sangre | B43: Arturo Pérez-Reverte | C43: ebook | D43: 45914 | E43: 45917 | F43: 264 | G43: Novela | H43: 8 | K43: 1997
A44: El sol de Breda | B44: Arturo Pérez-Reverte | C44: ebook | D44: 45917 | E44: 45921 | F44: 264 | G44: Novela | H44: 8 | K44: 1998
A45: El fin del imperio | B45: John Scalzi | C45: ebook | D45: 45921 | E45: 45932 | F45: 328 | G45: Novela | H45: 7.5 | K45: 2018
A46: El oro del rey | B46: Arturo Pérez-Reverte | C46: ebook | D46: 45921 | E46: 45930 | F46: 280 | G46: Novela | H46: 8 | K46: 2000
A47: Throy | B47: Jack Vance | C47: ebook | D47: 45930 | E47: 45943 | F47: 256 | G47: Novela | H47: 6 | K47: 1992
A48: El imperio en llamas | B48: John Scalzi | C48: ebook | D48: 45932 | E48: 45940 | F48: 312 | G48: Novela | H48: 8 | K48: 2018
A49: La conquista de México | B49: Hugh Thomas | C49: ebook | D49: 45940 | E49: 45973 | F49: 1135 | G49: Novela | H49: 9 | K49: 1994
A50: Amanecer rojo | B50: Pierce Brown | C50: ebook | D50: 45943 | E50: 45974 | F50: 544 | G50: Novela | H50: 6 | K50: 2014
A51: Vida, la gran historia | B51: Juan Luis Arsuaga | C51: Propio | D51: 45951 | E51: 45992 | F51: 587 | G51: Ensayo | H51: 8 | K51: 2019
A52: Come, reza, ama | B52: Liz Gilbert | C52: ebook | D52: 45974 | E52: 45984 | F52: 456 | G52: Viajes | H52: 8 | K52: 2006
A53: Anatomía de un instante | B53: Javier Cercas | C53: ebook | D53: 45982 | E53: 45997 | F53: 480 | G53: Ensayo | H53: 8 | K53: 2009
... A57: Mala hierba | B57: Pio Baroja | C57: ebook | D57: 46017 | E57: 46387 | F57: 281 | G57: Novela | H57: 6 | K57: 1904
F58: =SUMIFS(F2:F57,E2:E57,">0") -> 22196 | H58: =GEOMEAN(H2:H4) -> 7.3186114 | I58: =NA() -> #N/A | J58: =NA() -> #N/A
A59: Estadísticas | I59: =NA() -> #N/A | J59: =NA() -> #N/A
A60: Libros Leídos | B60: Media páginas por libro | C60: Autor más leido | D60: Tipo más leido | I60: =NA() -> #N/A | J60: =NA() -> #N/A
A61: =COUNTIF(E2:E57,">0") -> 56 | B61: =ROUND(F58/A61,0) -> 396 | C61: =INDEX(J2:J82,MATCH(MAX(I2:I82),I2:I82,0),1) -> #N/A | I61: =NA() -> #N/A | J61: =NA() -> #N/A
I62: =NA() -> #N/A | J62: =NA() -> #N/A
I63: =NA() -> #N/A | J63: =NA() -> #N/A
I64: =NA() -> #N/A | J64: =NA() -> #N/A
I65: =NA() -> #N/A | J65: =NA() -> #N/A
I66: =NA() -> #N/A | J66: =NA() -> #N/A
I67: =NA() -> #N/A | J67: =NA() -> #N/A
I68: =NA() -> #N/A | J68: =NA() -> #N/A
I69: =NA() -> #N/A | J69: =NA() -> #N/A
I70: =NA() -> #N/A | J70: =NA() -> #N/A
I71: =NA() -> #N/A | J71: =NA() -> #N/A
I72: =NA() -> #N/A | J72: =NA() -> #N/A
I73: =NA() -> #N/A | J73: =NA() -> #N/A
... I82: =NA() -> #N/A | J82: =NA() -> #N/A

Sheet Leídos 2026
A1: Titulo | B1: Autor | C1: Origen | D1: Fecha Inicio | E1: Fecha Fin | F1: Paginas | G1: Tipo | H1: Puntuación (del 1 al 10) | I1: Num leidos | J1: Autor | K1: Año
A2: (Ekumen 4) La mano izquierda de la oscuridad | B2: Ursula K. Le Guin | C2: ebook | D2: 43318 | F2: 304 | G2: Novela | K2: 1969
A3: Otros mundos | B3: Thomas Halliday | C3: Propio | D3: 44860 | F3: 416 | G3: Ensayo | K3: 2022
A4: La divina comedia | B4: Dante Alighlieri | C4: Propio | D4: 44929 | F4: 668 | G4: Poesia | K4: 1320
A5: La guerra de la paz | B5: Vernor Vinge | C5: ebook | D5: 44406 | F5: 384 | G5: Novela | K5: 1984
A6: Accelerando | B6: Charles Stross | C6: Propio | D6: 45124 | F6: 351 | G6: Novela | K6: 2005
A7: El origen de las especies | B7: Charles Darwin | C7: Propio | F7: 676 | G7: Ensayo | K7: 2019
A8: Abrázame hasta que esta vida deje de dar puto asco | B8: Juarma | C8: Propio | F8: 150 | G8: Comic | K8: 2022
A9: Rayuela | B9: Julio Cortazar | C9: Propio | F9: 746 | G9: Novela | K9: 1984
A10: Meditaciones | B10: Ignatius Farray | C10: Propio | F10: 218 | G10: Ensayo | K10: 2022
A11: Historia de la literatura romana | B11: Ludwig Bieler | C11: Propio | D11: 45231 | F11: 336 | G11: Historia | K11: 1972
A12: Japan Sinks | B12: Sakyo Komatsu | C12: Propio | D12: 45328 | F12: 494 | G12: Novela | K12: 1973
A13: TEOGONIA / TRABAJOS Y DIAS / ESCUDO / CERTAMEN | B13: Hesiodo | C13: Propio | D13: 45826 | F13: 216 | G13: Poesia | K13: -700
A14: El mito de Esparta | B14: César Fornis | C14: Propio | D14: 45992 | E14: 46027 | F14: 386 | G14: Ensayo | H14: 8 | K14: 2019
A15: Paladín de almas | B15: Lois McMaster Bujold | C15: ebook | D15: 46023 | E15: 46098 | F15: 352 | G15: Novela | H15: 8 | K15: 2003
A16: Gerona | B16: Benito Pérez Galdós | C16: ebook | D16: 46023 | E16: 46086 | F16: 192 | G16: Novela | H16: 7 | K16: 1874
A17: En carne alienígena | B17: Gregory Benford | C17: ebook | D17: 46023 | E17: 46057 | F17: 355 | G17: Novela | H17: 8 | K17: 1989
A18: Cuentos completos 1 | B18: Philip K. Dick | C18: Propio | D18: 46027 | E18: 46067 | F18: 651 | G18: Relatos | H18: 8 | K18: 1987
A19: Hades, el dios menos malo | B19: Pol Gisa | C19: Propio | D19: 46036 | F19: 208 | G19: Novela | K19: 2025
A20: La casa de Aizgorri | B20: Pio Baroja | C20: ebook | D20: 46058 | E20: 46082 | F20: 144 | G20: Novela | H20: 6 | K20: 1900
A21: El bigote | B21: Emmanuelle Carrére | C21: Propio | D21: 46067 | E21: 46078 | F21: 184 | G21: Novela | H21: 8 | K21: 2014
A22: Black Metal | B22: Magius | C22: Propio | D22: 46029 | F22: 220 | G22: Comic | K22: 2024
A23: La historia silenciada | B23: Rafael Vilchez Sanso | C23: Propio | D23: 46075 | E23: 46082 | F23: 200 | G23: Historia | H23: 8 | K23: 2025
A24: El vacío de la evolución | B24: Peter Hamilton | C24: ebook | D24: 46082 | E24: 46176 | F24: 544 | G24: Novela | H24: 7 | K24: 2013
A25: “1493” | B25: Charles C. Mann | C25: Propio | D25: 46078 | E25: 46123 | F25: 735 | G25: Historia | H25: 9 | K25: 2011
A26: Los pazos de Ulloa | B26: Emilia Pérez Bazán | C26: ebook | D26: 46101 | E26: 46194 | F26: 480 | G26: Novela | H26: 7 | K26: 1886
A27: Dormir en un mar de estrellas | B27: Christopher Paolini | C27: ebook | D27: 46106 | E27: 46216 | F27: 888 | G27: Novela | H27: 7 | K27: 2020
A28: Carlos V | B28: Geoffrey Parker | C28: Propio | D28: 46113 | E28: 46171 | F28: 990 | G28: Historia | H28: 8 | K28: 1993
A29: Los indoeuropeos | B29: J.P. Mallory | C29: Propio | D29: 46151 | E29: 46199 | F29: 456 | G29: Historia | H29: 7 | K29: 2025
A30: “1491” | B30: Charles C. Mann | C30: Propio | D30: 46171 | E30: 46194 | F30: 688 | G30: Historia | H30: 9 | K30: 2005
A31: El puente de los asesinos | B31: Arturo Pérez Reverte | C31: ebook | D31: 46176 | E31: 46203 | F31: 368 | G31: Novela | H31: 8 | K31: 2011
A32: La gran invención | B32: Silvia Ferrara | C32: Propio | D32: 46202 | E32: 46206 | F32: 391 | G32: Ensayo | H32: 9.5 | K32: 2022
A33: El barman del Ritz | B33: Philippe Collin | C33: Propio | D33: 46196 | E33: 46215 | F33: 391 | G33: Novela | H33: 7.7 | K33: 2024
A34: Shakespeare | B34: Bill Bryson | C34: ebook | D34: 46203 | E34: 46206 | F34: 240 | G34: Ensayo | H34: 9 | K34: 2007
... A40: Prehistoria | B40: Alfonso Moure | C40: ebook | D40: 46241 | E40: 46252 | F40: 320 | G40: Historia | H40: 5 | K40: 1990
A41: La búsqueda de la lengua perfecta | B41: Umberto Eco | C41: ebook | D41: 46241 | F41: 320 | G41: Ensayo | K41: 1994
A42: El visitante inesperado | B42: John Scalzi | C42: ebook | D42: 46244 | E42: 46247 | F42: 288 | G42: Novela | H42: 7 | K42: 2012
A43: Juan Martin, el Empecinado | B43: Benito Pérez Galdós | C43: ebook | D43: 46244 | E43: 46252 | F43: 240 | G43: Novela | H43: 7 | K43: 1874
A44: La luna es un cruel amante | B44: Robert A. Heinlein | C44: ebook | D44: 46248 | E44: 46269 | F44: 463 | G44: Novela | H44: 8.7 | K44: 1965
A45: Asfixia | B45: Chuck Palahniuk | C45: ebook | D45: 46253 | F45: 336 | G45: Novela | K45: 2001
A46: Intrusos siderales | B46: Pascual Eguindano | C46: Propio | D46: 46269 | E46: 46271 | F46: 139 | G46: Novela | K46: 1951
A47: Cántico por Leibowitz | B47: Walter M. Miller | C47: ebook | D47: 46253 | E47: 46295 | F47: 336 | G47: Novela | H47: 8 | K47: 1959
A48: El antiguo Oriente Próximo | B48: Amanda H. Podany | C48: Propio | D48: 46271 | E48: 46280 | F48: 211 | G48: Historia | H48: 8 | K48: 2001
A49: Lo mejor de la ciencia ficción española | B49: Domingo Santos (coord.) | C49: Propio | D49: 46280 | F49: 320 | G49: Novela | K49: 1985
A50: Maniac | B50: Benjamin Labatut | C50: Propio | D50: 46293 | F50: 400 | G50: Ensayo | K50: 2023
A51: Granada la Bella | B51: Angel Ganivet | C51: ebook | D51: 46295 | E51: 46297 | F51: 120 | G51: Ensayo | K51: 1897
A52: Matar a un ruiseñor | B52: Harper Lee | C52: ebook | D52: 46297 | F52: 416 | G52: Novela | K52: 1960
F53: =SUMIFS(F2:F52,E2:E52,">0") -> 13163 | H53: =GEOMEAN(H2:H52) -> 7.7360712 | I53: =NA() -> #N/A | J53: =NA() -> #N/A
A54: Estadísticas | I54: =NA() -> #N/A | J54: =NA() -> #N/A
A55: Libros Leídos | B55: Media páginas por libro | C55: Autor más leido | D55: Tipo más leido | I55: =NA() -> #N/A | J55: =NA() -> #N/A
A56: =COUNTIF(E2:E52,">0") -> 32 | B56: =ROUND(F53/A56,0) -> 411 | C56: =INDEX(J3:J77,MATCH(MAX(I3:I77),I3:I77,0),1) -> #N/A | I56: =NA() -> #N/A | J56: =NA() -> #N/A
I57: =NA() -> #N/A | J57: =NA() -> #N/A
I58: =NA() -> #N/A | J58: =NA() -> #N/A
I59: =NA() -> #N/A | J59: =NA() -> #N/A
I60: =NA() -> #N/A | J60: =NA() -> #N/A
I61: =NA() -> #N/A | J61: =NA() -> #N/A
I62: =NA() -> #N/A | J62: =NA() -> #N/A
I63: =NA() -> #N/A | J63: =NA() -> #N/A
I64: =NA() -> #N/A | J64: =NA() -> #N/A
I65: =NA() -> #N/A | J65: =NA() -> #N/A
I66: =NA() -> #N/A | J66: =NA() -> #N/A
I67: =NA() -> #N/A | J67: =NA() -> #N/A
I68: =NA() -> #N/A | J68: =NA() -> #N/A
... I77: =NA() -> #N/A | J77: =NA() -> #N/A

Sheet Gráficos
B34: Año | C34: Libros | D34: Páginas | E34: Media por libro | F34: Media páginas anual | G34: PPD
B35: 2010 | C35: ='Leidos 2010'!B61 -> 56 | D35: ='Leidos 2010'!A61 -> 20051 | E35: ='Leidos 2010'!C61 -> 358 | F35: =HARMEAN(D35) -> 20051 | G35: =D35/365 -> 54.934247
B36: 2011 | C36: ='Leidos 2011'!A53 -> 48 | D36: ='Leidos 2011'!F50 -> 18918 | E36: ='Leidos 2011'!B53 -> 394 | F36: =HARMEAN(D35:D36) -> 19468.029 | G36: =D36/365 -> 51.830137
B37: 2012 | C37: ='Leidos 2012'!A58 -> 52 | D37: ='Leidos 2012'!F55 -> 19868 | E37: ='Leidos 2012'!B58 -> 382 | F37: =HARMEAN(D35:D37) -> 19599.551 | G37: =D37/365 -> 54.432877
B38: 2013 | C38: ='Leídos 2013'!A44 -> 27 | D38: ='Leídos 2013'!F41 -> 17259 | E38: ='Leídos 2013'!B44 -> 639 | F38: =HARMEAN(D35:D38) -> 18956.851 | G38: =D38/365 -> 47.284932
B39: 2014 | C39: ='Leídos 2014'!A29 -> 12 | D39: ='Leídos 2014'!F26 -> 8907 | E39: ='Leídos 2014'!B29 -> 742 | F39: =HARMEAN(D35:D39) -> 15466.624 | G39: =D39/365 -> 24.40274
B40: 2015 | C40: ='Leídos 2015'!A47 -> 27 | D40: ='Leídos 2015'!F44 -> 11891 | E40: ='Leídos 2015'!B47 -> 440 | F40: =HARMEAN(D35:D40) -> 14728.481 | G40: =D40/365 -> 32.578082
B41: 2016 | C41: ='Leídos 2016'!A53 -> 35 | D41: ='Leídos 2016'!F50 -> 13222 | E41: ='Leídos 2016'!B53 -> 378 | F41: =HARMEAN(D35:D41) -> 14492.589 | G41: =D41/365 -> 36.224658
B42: 2017 | C42: ='Leídos 2017'!A45 -> 26 | D42: ='Leídos 2017'!F42 -> 12899 | E42: ='Leídos 2017'!B45 -> 496 | F42: =HARMEAN(D35:D42) -> 14272.184 | G42: =D42/365 -> 35.339726
B43: 2018 | C43: ='Leídos 2018'!A47 -> 29 | D43: ='Leídos 2018'!F44 -> 11755 | E43: ='Leídos 2018'!B47 -> 405 | F43: =HARMEAN(D35:D43) -> 13940.497 | G43: =D43/365 -> 32.205479
B44: 2019 | C44: ='Leídos 2019'!A30 -> 22 | D44: ='Leídos 2019'!F27 -> 10870 | E44: ='Leídos 2019'!B30 -> 494 | F44: =HARMEAN(D35:D44) -> 13557.532 | G44: =D44/365 -> 29.780822
B45: 2020 | C45: ='Leídos 2020'!A48 -> 40 | D45: ='Leídos 2020'!F45 -> 14579 | E45: ='Leídos 2020'!B48 -> 364 | F45: =HARMEAN(D35:D45) -> 13644.44 | G45: =D45/365 -> 39.942466
B46: 2021 | C46: ='Leídos 2021'!A34 -> 24 | D46: ='Leídos 2021'!F31 -> 7908 | E46: ='Leídos 2021'!B34 -> 330 | F46: =HARMEAN(D35:D46) -> 12866.654 | G46: =D46/365 -> 21.665753
B47: 2022 | C47: ='Leídos 2022'!A47 -> 35 | D47: ='Leídos 2022'!F44 -> 13862 | E47: ='Leídos 2022'!B47 -> 396 | F47: =HARMEAN(D35:D47) -> 12938.116 | G47: =D47/365 -> 37.978082
B48: 2023 | C48: ='Leídos 2023'!A52 -> 47 | D48: ='Leídos 2023'!F49 -> 17489 | E48: ='Leídos 2023'!B52 -> 372 | F48: =HARMEAN(D35:D48) -> 13183.147 | G48: =D48/365 -> 47.915068
B49: 2024 | C49: ='Leídos 2024'!A75 -> 58 | D49: ='Leídos 2024'!F72 -> 23457 | E49: ='Leídos 2024'!B75 -> 404 | F49: =HARMEAN(D35:D49) -> 13579.661 | G49: =D49/365 -> 64.265753
B50: 2025 | C50: ='Leídos 2025'!A61 -> 56 | D50: ='Leídos 2025'!F58 -> 22196 | E50: ='Leídos 2025'!B61 -> 396 | F50: =HARMEAN(D36:D50) -> 13639.173 | G50: =D50/365 -> 60.810959
B51: 2026 | C51: ='Leídos 2026'!A56 -> 32 | D51: ='Leídos 2026'!F53 -> 13163 | E51: ='Leídos 2026'!B56 -> 411 | F51: =HARMEAN(D35:D51) -> 13870.567 | G51: =D51/365 -> 36.063014
B53: Media | C53: =TRIMMEAN(C34:C51,10%) -> 36.823529 | D53: =TRIMMEAN(D34:D51,10%) -> 15193.765
B54: Total | C54: =SUM(C35:C52) -> 626

Sheet kindle
A1: Titulo | B1: Autor | C1: Origen | D1: Fecha Inicio | E1: Fecha Fin | F1: Paginas | G1: Tipo
A2: Donde las mujeres | B2: Alvaro Pombo | C2: ebook | F2: 288 | G2: Novela
A3: La fortuna de Matilda Turpin | B3: Alvaro Pombo | C3: ebook | F3: 442 | G3: Novela
A4: Una mujer en Berlín | B4: Anónimo | C4: ebook | F4: 336 | G4: Historia
A5: Recopilación de cuentos | B5: Anton Chejov | C5: ebook
A6: La muerte de Carlos… | B6: Antonio Lobo Antunes | C6: ebook | G6: Novela
A7: El niño asombrado | B7: Antonio Rabinad | C7: ebook | G7: Novela
A8: El cartero de Neruda | B8: Antonio Skarmeta | C8: ebook | F8: 144 | G8: Novela
A9: Sostiene Pereira | B9: Antonio Tabucchi | C9: ebook | F9: 220 | G9: Novela
A10: El misterio de Olga Chejova | B10: Antony Beevor | C10: ebook | F10: 320 | G10: Historia
A11: Las últimas cartas de Stalingrado | B11: Antony Beevor | C11: ebook | F11: 112 | G11: Historia
A12: Dinero | B12: Aristofanes | C12: ebook | G12: Teatro
A13: El capitán Alatriste | B13: Arturo Pérez-Reverte | C13: ebook | F13: 248 | G13: Novela
A14: El oro del rey | B14: Arturo Pérez-Reverte | C14: ebook | F14: 267 | G14: Novela
A15: El sol de Breda | B15: Arturo Pérez-Reverte | C15: ebook | F15: 264 | G15: Novela
A16: Como ser un sinvergüenza con las mujeres | B16: Arturo Rosby | C16: ebook | G16: Novela
A17: El bajo imperio romano | B17: Averil Cameron | C17: ebook | G17: Historia
A18: Antropología de la pornografía | B18: Bernard Arcand | C18: ebook | G18: Antropología
A19: El lector | B19: Bernhard Schlink | C19: ebook | F19: 208 | G19: Novela
A20: Luna park | B20: Bret Easton Ellis | C20: N ELL lun | F20: 380 | G20: Novela
A21: Cosmos | B21: Carl Sagan | C21: ebook | F21: 384 | G21: Ensayo
A22: Los caminantes | B22: Carlos Sisi | C22: ebook | G22: Novela
A23: La Búsqueda de las Especias | B23: Carson I. A. Ritchie | C23: ebook | G23: Historia
A24: La estación de la calle perdida | B24: China Mieville | C24: ebook | G24: Novela
A25: La Sanguijuela de mi niña | B25: Christopher Moore | C25: ebook | F25: 320 | G25: Novela
A26: Nana | B26: Chuck Palahniuk | C26: ebook | F26: 272 | G26: Novela
A27: Maldito karma | B27: David Safier | C27: ebook | G27: Novela
A28: Hablemos de langostas | B28: David Wallace | C28: ebook | G28: Novela
A29: El desierto de los Tártaros | B29: Dino Buzzati | C29: N BUZ des | F29: 271 | G29: Novela
A30: La guerra del Peloponeso | B30: Donald Kagan | C30: ebook | G30: Historia
A31: Por qué somos como somos | B31: Eduardo Punset | C31: 612 PUN por | F31: 295 | G31: Ensayo
A32: El tiempo de los trenes | B32: Fernando Fernán Gómez | C32: ebook | G32: Novela
A33: Los usurpadores | B33: Francisco Ayala | C33: ebook | G33: Novela
A34: Muertes de perro | B34: Francisco Ayala | C34: ebook | G34: Novela
A35: Las sombras de la catedral | B35: Frank Schätzing | C35: ebook | G35: Novela
A36: El castillo | B36: Franz Kafka | C36: ebook | G36: Novela
A37: Cien años de soledad | B37: Gabriel García Márquez | C37: N GAR cie | G37: Novela
A38: El viajero | B38: Gary Jennings | C38: ebook | G38: Novela
A39: Sangre azteca | B39: Gary Jennings | C39: N JEN azt | F39: 1085 | G39: Novela
A40: Homenaje a Cataluña | B40: George Orwell | C40: ebook | G40: Historia
A41: My family and other animals | B41: Gerald Durrell | C41: N DUR mif | F41: 374 | G41: Novela
A42: El gatopardo | B42: Giuseppe Tomasi Di Lampedusa | C42: ebook | G42: Novela
A43: Mesias | B43: Gore Vidal | C43: ebook | G43: Novela
A44: El tambor de hojalata | B44: Günter Grass | C44: N GRA tam | F44: 655 | G44: Novela
A45: El golem | B45: Gustav Meyrink | C45: ebook | G45: Novela
A46: Madame Bovary | B46: Gustave Flaubert | C46: N FLA mad | F46: 445 | G46: Novela
A47: Sauce ciego, mujer dormida | B47: Haruki Murakami | C47: ebook | G47: Novela
A48: El tren llegó puntual | B48: Heinrich Boll | C48: ebook | G48: Novela
A49: El ojo del leopardo | B49: Henning Mankell | C49: ebook | G49: Novela
A50: Moby dick | B50: Herman Melville | C50: ebook | G50: Novela
A51: El mundo sumergido | B51: J. G. Ballard | C51: ebook | G51: Novela
A52: Esperare en Murak | B52: J. G. Ballard | C52: N BAL cra | F52: 249 | G52: Novela
A53: Mundo sumergido | B53: J. G. Ballard | C53: N BAL mun | F53: 221 | G53: Novela
A54: Los vagabundos del Dharma | B54: Jack Kerouac | C54: ebook | G54: Novela
A55: La civilización del Occidente | B55: Jacques Le Goff | C55: ebook | G55: Historia
A56: Los intelectuales de la Edad Media | B56: Jacques Le Goff | C56: ebook | G56: Historia
A57: Sangre vagabunda | B57: James Ellroy | C57: ebook | G57: Novela
A58: Dublineses | B58: James Joyce | C58: ebook | G58: Novela
A59: El fabuloso libro de las leyendas urbanas | B59: Jan Harold Brunvand | C59: N BRU fab 1 | F59: 347 | G59: Ensayo
A60: La maestra de piano | B60: Janice y K Lee | C60: ebook | G60: Novela
A61: Porqué es divertido el sexo | B61: Jared Diamond | C61: ebook | G61: Ensayo
A62: Anatomía de un instante | B62: Javier Cercas | C62: N CER ana | F62: 461 | G62: Novela
A63: Las uvas de la ura | B63: John Steinbeck | C63: ebook | G63: Novela
A64: Caín | B64: José Saramago | C64: ebook | G64: Novela
A65: El hombre duplicado | B65: José Saramago | C65: ebook | G65: Novela
A66: Memorial del Convento | B66: José Saramago | C66: ebook | G66: Novela
A67: Burlando a la parca | B67: Josh Bazell | C67: ebook | G67: Novela
A68: Rabos de lagartija | B68: Juan Marsé | C68: ebook | G68: Novela
A69: La crisis financiera | B69: Juan Torres López | C69: ebook | G69: Ensayo
A70: La iglesia de Franco | B70: Julian Casanova | C70: ebook | G70: Historia
A71: La guerra de las salamandras | B71: Karel Capek | C71: N CAP gue | F71: 292 | G71: Novela
A72: Volver a empezar | B72: Ken Grimwood | C72: ebook | G72: Novela
A73: El perro lanudo de Tom Edison | B73: Kurt Vonnegut | C73: ebook | G73: Novela
A74: Galápagos | B74: Kurt Vonnegut | C74: ebook | G74: Novela
A75: Hocus pocus | B75: Kurt Vonnegut | C75: ebook | G75: Novela
A76: La pianola | B76: Kurt Vonnegut | C76: ebook | G76: Novela
A77: Payasadas | B77: Kurt Vonnegut | C77: ebook | G77: Novela
A78: El hipnotista | B78: Lars Kepler | C78: ebook | G78: Novela
A79: Carta Blanca | B79: Lorenzo Silva | C79: N SIL car | F79: 346 | G79: Novela
A80: El hombre que calculaba | B80: Malba Tahan | C80: ebook | G80: Novela
A81: Andamios | B81: Mario Benedetti | C81: ebook | G81: Novela
A82: La cuarta K | B82: Mario Puzo | C82: ebook | G82: Novela
A83: Los borgia | B83: Mario Puzo | C83: ebook | G83: Historia
A84: Antropologia cultural | B84: Marvin Harris | C84: ebook | G84: Antropología
A85: Vacas, cerdos, guerras y brujas : los enigmas de la cultura | B85: Marvin Harris | C85: 39 HAR vac | F85: 247 | G85: Antropología
A86: Cinco horas con Mario | B86: Miguel Delibes | C86: ebook | G86: Novela
A87: Mito y realidad | B87: Mircea Eliade | C87: ebook | G87: Antropología
A88: Neverwhere | B88: Neil Gaiman | C88: N GAI nev | F88: 303 | G88: Novela
A89: Así habló Zaratustra | B89: Nietzche | C89: ebook | G89: Ensayo
A90: La bodega | B90: Noah Gordon | C90: ebook | G90: Novela
A91: Cómo nos venden la moto | B91: Noam Chomsky | C91: ebook | G91: Ensayo
A92: Historia de la pirateria | B92: Philip Gosse | C92: ebook | G92: Historia
A93: Mensajero del futuro | B93: Poul Anderson | C93: ebook | G93: Novela
A94: Lo contrario de la muerte | B94: Roberto Saviano | C94: ebook | G94: Novela
A95: Kim | B95: Rudyard Kipling | C95: ebook | G95: Novela
A96: Historia de Roma Libro 1 y 2 | B96: Theodor Mommsen | C96: ebook | G96: Historia
A97: La muerte en Venecia | B97: Thomas Mann | C97: ebook | G97: Novela
A98: Mosquitos | B98: William Faulkner | C98: ebook | G98: Novela
A99: Quemando cromo | B99: William Gibson | C99: N GIB que | G99: Novela
A100: El pianista del gueto de Varsovia | B100: Wladyslaw Szplitz | C100: ebook | G100: Novela
...

Sheet Proxima Visita
A1: Titulo | B1: Autor | C1: Origen | D1: Fecha Inicio | E1: Fecha Fin | F1: Paginas | G1: Tipo | H1: Puntuación (del 1 al 10)

Sheet Pendientes
A1: Titulo | B1: Autor | C1: Origen | D1: Fecha Inicio | E1: Fecha Fin | F1: Paginas | G1: Tipo | H1: Puntuación (del 1 al 10)
A2: Este libro te salvará la vida | B2: A.M. Homes | C2: N HOM est | F2: 392 | G2: Novela
A3: Viaje al fin del milenio | B3: Abraham B. Yehoshúa | C3: N YEH via | F3: 407 | G3: Novela
A4: De jardines ajenos (Libro abierto) | B4: Adolfo Bioy Casares | C4: N BIO dej | F4: 309 | G4: Novela
A5: La analfabeta | B5: Agota Kristof | C5: N KRI ana | F5: 78 | G5: Novela
A6: Nocilla experience | B6: Agustín Fernández Mallo | C6: N FER noc | F6: 205 | G6: Novela
A7: Vía férrea | B7: Aharon Appelfeld | C7: N FER aha | F7: 195 | G7: Novela-Shoa
A8: Reino de sombras | B8: Alan Furst | C8: N FUR rei | F8: 300 | G8: Novela
A9: Espacio revelación | B9: Alastair Reynolds | C9: N REY esp | F9: 385 | G9: Novela
A10: El Trienio liberal | B10: Alberto Gil Novales | C10: 946 GIL tri | F10: 146 | G10: Historia
A11: Los girasoles ciegos | B11: Alberto Méndez | C11: N MEN gir | F11: 155 | G11: Novela
A12: La reina Margot | B12: Alejandro Dumas | C12: N DUM rei | F12: 815 | G12: Novela
A13: El reino de este mundo | B13: Alejo Carpentier | C13: N CAR rei | F13: 144 | G13: Novela
... A71: América | B71: Franz Kafka | C71: N KAF ame | F71: 318 | G71: Novela
A72: Memoria de mis putas tristes | B72: Gabriel García Márquez | C72: N GAR mem | G72: Novela
A73: Introducción a la España medieval | B73: Gabriel Jackson | C73: 946 JAC int | F73: 166 | G73: Historia
A74: Biografía de la física | B74: George Gamow | C74: 53(09) GAM bio | F74: 414 | G74: Ensayo
A75: Pastoralia | B75: George Saunders | C75: N SAU pas | F75: 168 | G75: Novela
A76: Lo que está mal en el mundo | B76: Gilbert K. Chesterton | C76: 316 CHE loq | F76: 206 | G76: Ensayo
A77: Imperio | B77: Gore Vidal | C77: N VID imp | F77: 500 | G77: Novela
A78: Los comediantes | B78: Graham Greene | C78: N GRE com | F78: 360 | G78: Novela
A79: Ciudad permutación | B79: Greg Eagan | C79: N GEA ciu | F79: 342 | G79: Novela
A80: El libro de los hechos insólitos | B80: Gregorio Doval | C80: 088 DOV enc | F80: 372 | G80: Ensayo
A81: La casa Tellier y otros cuentos eróticos | B81: Guy de Maupassant | C81: N MAU cas | F81: 225 | G81: Novela
A82: Pyongyang | B82: Guy Delisle | C82: C-E DEL pyo | F82: 176 | G82: Comic - Viajes
A83: Animales y más que animales | B83: H.H. Munro Saki | C83: N SAK ani | F83: 184 | G83: Novela
A84: Cuando Kafka vino hacia mí | B84: Hans-Gerd Koch | C84: B KAF cua | F84: 279 | G84: Biografía-Historia
... A101: Gran Sol | B101: Ignacio Aldecoa | C101: N ALD gra | F101: 294 | G101: Novela
A102: La sangre de los inocentes | B102: Isabel Navarro | C102: N NAV san | G102: Novela
A103: La Biblia desenterrada | B103: Israel Finkelstein | C103: 933 FIN bib | F103: 414 | G103: Historia-Arqueología
A104: Un puente sobre el Drina | B104: Ivo Andric | C104: XXXXXX | F104: 448 | G104: Ensayo
A105: Crash | B105: J. G. Ballard | C105: N BAL cra | F105: 249 | G105: Novela
A106: Un palacio para el rey : el Buen Retiro y la corte de Felipe IV | B106: J.H. Elliott | C106: M 728 BRO pal | F106: 303 | G106: Historia
A107: La rama dorada : magia y religión | B107: James Frazer | C107: 2-9 FRA ram | F107: 860 | G107: Ensayo
A108: Dos damas muy serias | B108: Jane Bowles | C108: XXXXXX | F108: 224 | G108: Novela
A109: Rostros en el agua | B109: Janet Frame | C109: N FRA ros | F109: 274 | G109: Novela
A110: Colapso: por qué unas sociedades perduran y otras desaparecen | B110: Jared Diamond | C110: 008 DIA col | F110: 747 | G110: Ensayo
A111: El inquilino | B111: Javier Cercas | C111: N CER inq | F111: 138 | G111: Novela
A112: Los orígenes del pensamiento reaccionario español | B112: Javier Herrero | C112: 329 HER ori | F112: 428 | G112: Ensayo
A113: Tu rostro mañana 1. Fiebre y lanza | B113: Javier Marias | C113: N MAR tur 1 | G113: Novela
A114: Venga a nosotros tu reino | B114: Javier Reverte | C114: N MAR ven | F114: 526 | G114: Novela
A115: Siglo XX | B115: Javier Tusell | C115: 946 MAN tus 6 | F115: 939 | G115: Historia
A116: Ancho mar de los Sargazos | B116: Jean Rhys | C116: N RHY anc | F116: 186 | G116: Novela
A117: HIERRO en las espinacas y otras creencias | B117: Jean-François Bouvet | C117: 5/6 HIE | F117: 202 | G117: Ensayo
A118: En el día de hoy | B118: Jesús Torbado | C118: N TOR ene | F118: 361 | G118: Novela
A119: El libro negro de Carrillo | B119: JJ Esparza | C119: XXXXXX | F119: 250 | G119: Historia
A120: El libro negro del Comunismo | B120: JJ Esparza | C120: XXXXXX | G120: Historia
A121: Erase una vez un número | B121: John Allen Paulos | C121: 51 PAU era | F121: 205 | G121: Ensayo
A122: El libro de la nada | B122: John D. Barrow | C122: 510 BAR lib | F122: 430 | G122: Matemáticas
A123: Camino de Los Ángeles | B123: John Fante | C123: N FAN cam | F123: 195 | G123: Novela
A124: Sueños de Bunker Hill | B124: John Fante | C124: N FAN sue | F124: 150 | G124: Novela
A125: Historia de las armas y guerras | B125: John Guy | C125: XXXXXX | G125: Historia
A126: American apocalypse | B126: John Kessel | C126: N KES ame | F126: 371 | G126: Novela
A127: El pequeño gran libro de la ignorancia (animal) | B127: John Lloyd | C127: 088 LLO peq | F127: 220 | G127: Ensayo
A128: Cinco días en Londres, mayo de 1940 : Churchill frente a Hitler | B128: John Lukacs | C128: 94 LUK cin | F128: 256 | G128: Historia
A129: El Hitler de la historia | B129: John Lukacs | C129: B HIT luk | F129: 293 | G129: Biografía-Historia
A130: En busca del candidato de Manchuria | B130: John Marks | C130: 327 MAR enb | F130: 421 | G130: Ensayo
A131: Corre, conejo | B131: John Updike | C131: N UPD cor | F131: 366 | G131: Novela
A132: Manual de supervivencia | B132: John Wiseman | C132: 614 WIS man | F132: 287 | G132: Ensayo
A133: Tantas maneras de empezar | B133: Jon McGregor | C133: N MCG tan | F133: 379 | G133: Novela
A134: La dama número trece | B134: José Carlos Somoza | C134: N SOM dam | F134: 453 | G134: Novela
A135: También se divierte el pueblo | B135: José Deleito y Piñuela | C135: 946 DEL tam | F135: 298 | G135: Historia
A136: Roma en guerra | B136: José Ignacio Lago | C136: 355 LAG rom | F136: 367 | G136: Historia
A137: Bajarse al moro | B137: José Luis Alonso de Santos | C137: T ALO baj | F137: 193 | G137: Teatro
... A143: Catch-22 | B143: Joseph Heller | C143: N HEL tra | F143: 649 | G143: Novela
A144: Breve historia del Satanismo | B144: Joseph McCabe | C144: XXXXXX | G144: Ensayo
A145: Náufragos de antaño | B145: Juan Campos Calvo Sotelo | C145: 656 CAM nau | F145: 415 | G145: Ensayo
A146: Ni pies ni cabeza | B146: Juan Carlos Córdoba | C146: XXXXXX | F146: 336 | G146: Novela
A147: Guerra y vicisitudes de los españoles | B147: Julián Zugazagoitia | C147: 946 ZUG gue | F147: 648 | G147: Historia
A148: El cielo de Madrid | B148: Julio Llamazares | C148: N LLA cie | F148: 256 | G148: Novela
A149: Todos los jóvenes tristes y literarios | B149: Keith Gessen | C149: N GES tod | F149: 277 | G149: Novela
A150: Mil soles espléndidos | B150: Khaled Hosseini | C150: N HOS mil | F150: 382 | G150: Novela
A151: La suerte de Jim | B151: Kingsley Amis | C151: N AMI sue | F151: 334 | G151: Novela
A152: Mundo anillo | B152: Larry Niven | C152: N NIV mun | F152: 523 | G152: Novela
A153: El partido de Londres | B153: Len Deighton | C153: N DEI par | F153: 313 | G153: Novela
A154: ¿Cuánto pesa el alma? | B154: Len Fisher | C154: 5/6 FIS cua | F154: 270 | G154: Curiosidades
A155: Guerra y paz | B155: Leon Tolstoi | C155: N TOL gue | F155: 1174 | G155: Novela
A156: La muerte de Iván Ilitch | B156: Leon Tolstoi | C156: N TOL mue | F156: 152 | G156: Novela
... A161: Inteligencia intuitiva | B161: Malcolm Gladwell | C161: 159 GLA int | F161: 293 | G161: Ensayo
A162: La clave del éxito | B162: Malcolm Gladwell | C162: 159 GLA cla | G162: Ensayo
A163: Iberia: la puerta iluminada | B163: Manuel de Lope | C163: N LOP ibe | F163: 479 | G163: Novela
A164: Yo te diré:la verdadera historia de los últimos de Filipinas (1898-1998) | B164: Manuel Leguineche | C164: 959 LEG yot | F164: 483 | G164: Historia
A165: Capitán de las sardinas | B165: Manuel Manzano | C165: N MAN cap | G165: Novela
A166: Los libros arden mal | B166: Manuel Rivas | C166: N RIV lib | F166: 610 | G166: Novela
A167: La gran tentación: Franco, el imperio colonial y el proyecto de intervención española en la Segunda Guerra Mundial | B167: Manuel Ros Agudo | C167: 946 ROS gra | F167: 413 | G167: Historia
A168: Los celtas | B168: Manuel Yáñez Solana | C168: 936 YAÑ cel | F168: 192 | G168: Historia
A169: País íntimo | B169: Maria Barbal | C169: N BAR pai | F169: 382 | G169: Novela
A170: La tregua | B170: Mario Benedetti | C170: N BEN tre | F170: 255 | G170: Novela
A171: La proporción Áurea | B171: Mario Livio | C171: 51 LIV pro | F171: 302 | G171: Matemáticas
A172: Quieto | B172: Màrius Serra | C172: N SER qui | F172: 156 | G172: Novela
A173: Alejandro Magno | B173: Mary Renault | C173: B ALE ren | F173: 255 | G173: Biografía-Historia
A174: Isaiah Berlin : Su vida | B174: Michael Ignatieff | C174: B BER ign | F174: 478 | G174: Biografía-Historia
A175: Plataforma | B175: Michel Houellebecq | C175: N HOU pla | F175: 316 | G175: Novela
A176: Hiperespacio | B176: Michio Kaku | C176: 514 KAK hip | F176: 520 | G176: Ensayo
A177: Un héroe de nuestro tiempo | B177: Mijaíl Lérmontov | C177: N LER her | F177: 251 | G177: Novela
... A189: Leviatán | B189: Paul Auster | C189: N AUS lev | F189: 269 | G189: Novela
A190: La Noche de los Cuchillos Largos | B190: Paul R. Maracin | C190: XXXXXX | G190: Historia
A191: Filosofía para bufones | B191: Pedro González Calero | C191: 1 GON fil | G191: Ensayo
A192: El reverso de la historia | B192: Pedro Voltes | C192: 94/99 VOL rev | F192: 415 | G192: Historia
A193: Conan Doyle, detective: los auténticos crímenes que investigó el creador de Sherlock Holmes | B193: Peter Costello | C193: B DOY cos | F193: 406 | G193: Ensayo
...

Sheet Descartados
A1: Titulo | B1: Autor | C1: Origen | D1: Fecha Inicio | E1: Fecha Fin | F1: Paginas | G1: Tipo | H1: Puntuación (del 1 al 10)
A3: Devoradores de cadáveres | B3: Michael Crichton | C3: N CRI dev
A4: Un Tiempo para Bailar, un Tiempo para Morir: La Historia Extraordinaria de la Plaga del Baile de 1518 | B4: John Waller
A5: La Alhambra hermética | B5: Antonio Enrique
A6: En el corazón del mar | B6: Nathaniel Philbrick | C6: Otras
A7: La historia del mundo en seis tragos : de la cerveza de los faraones a la Coca-Cola | B7: Tom Standage | C7: Otras
A8: Diccionario del crimen | B8: Oliver Cyriax | C8: Otras
A9: Polvo en marcha | B9: Rusty Young / Thomas McFadden
A10: El encuentro | B10: Frederik Pohl | C10: N POH sag 3 | F10: 346 | G10: Novela
A11: Conversaciones con Billy Wilder | B11: Cameron Crowe | C11: 791 WIL cro | F11: 365 | G11: Cine
A12: Asesinatos S.L. | B12: Jack London | C12: N LON ase | F12: 190 | G12: Novela
A13: Historia de los grandes burdeles del mundo | B13: Emmett Murphy | C13: 392 MUR his | F13: 350 | G13: Historia | I13: Biblioteca Central
A14: La Máquina Génesis | B14: James P. Hogan | C14: 09/21606 | F14: 347 | G14: Novela | I14: Biblioteca Regional de Madrid Joaquín Leguina
A15: La puta de Babilonia | B15: Fernando Vallejo | C15: No está
A16: Sex code : El manual práctico de los maestros de la seducción | B16: Mario Luna | C16: 159 LUN sex | F16: 672 | G16: Ensayo
